[{"Volume": "1519300", "Open": "28.50", "High": "28.700001", "Low": "27.00", "Date": "2017-03-03", "Adj_Close": "27.90", "Close": "27.90", "Symbol": "GBT"}, {"Volume": "4980700", "Open": "30.00", "High": "31.00", "Low": "26.35", "Date": "2017-03-02", "Adj_Close": "27.049999", "Close": "27.049999", "Symbol": "GBT"}, {"Volume": "1765900", "Open": "27.90", "High": "29.90", "Low": "27.200001", "Date": "2017-03-01", "Adj_Close": "29.75", "Close": "29.75", "Symbol": "GBT"}, {"Volume": "1380300", "Open": "28.299999", "High": "28.700001", "Low": "27.50", "Date": "2017-02-28", "Adj_Close": "27.85", "Close": "27.85", "Symbol": "GBT"}, {"Volume": "1422200", "Open": "28.25", "High": "29.60", "Low": "27.700001", "Date": "2017-02-27", "Adj_Close": "28.299999", "Close": "28.299999", "Symbol": "GBT"}, {"Volume": "1503800", "Open": "26.00", "High": "28.450001", "Low": "25.743999", "Date": "2017-02-24", "Adj_Close": "28.15", "Close": "28.15", "Symbol": "GBT"}, {"Volume": "2282900", "Open": "24.950001", "High": "26.40", "Low": "24.65", "Date": "2017-02-23", "Adj_Close": "26.25", "Close": "26.25", "Symbol": "GBT"}, {"Volume": "8234100", "Open": "25.60", "High": "26.50", "Low": "23.549999", "Date": "2017-02-22", "Adj_Close": "24.40", "Close": "24.40", "Symbol": "GBT"}, {"Volume": "1822100", "Open": "27.85", "High": "29.10", "Low": "27.25", "Date": "2017-02-21", "Adj_Close": "28.50", "Close": "28.50", "Symbol": "GBT"}, {"Volume": "1631700", "Open": "24.799999", "High": "28.00", "Low": "24.10", "Date": "2017-02-17", "Adj_Close": "26.90", "Close": "26.90", "Symbol": "GBT"}, {"Volume": "1612200", "Open": "23.35", "High": "26.049999", "Low": "22.700001", "Date": "2017-02-16", "Adj_Close": "24.950001", "Close": "24.950001", "Symbol": "GBT"}, {"Volume": "1553700", "Open": "22.299999", "High": "23.799999", "Low": "21.85", "Date": "2017-02-15", "Adj_Close": "23.35", "Close": "23.35", "Symbol": "GBT"}, {"Volume": "1168200", "Open": "20.799999", "High": "22.549999", "Low": "20.25", "Date": "2017-02-14", "Adj_Close": "22.40", "Close": "22.40", "Symbol": "GBT"}, {"Volume": "1722800", "Open": "21.50", "High": "23.00", "Low": "19.35", "Date": "2017-02-13", "Adj_Close": "20.50", "Close": "20.50", "Symbol": "GBT"}, {"Volume": "1991600", "Open": "19.700001", "High": "21.950001", "Low": "18.950001", "Date": "2017-02-10", "Adj_Close": "21.50", "Close": "21.50", "Symbol": "GBT"}, {"Volume": "1120000", "Open": "17.75", "High": "20.35", "Low": "17.700001", "Date": "2017-02-09", "Adj_Close": "19.700001", "Close": "19.700001", "Symbol": "GBT"}, {"Volume": "941200", "Open": "16.700001", "High": "18.200001", "Low": "16.65", "Date": "2017-02-08", "Adj_Close": "17.700001", "Close": "17.700001", "Symbol": "GBT"}, {"Volume": "675500", "Open": "16.200001", "High": "16.950001", "Low": "16.15", "Date": "2017-02-07", "Adj_Close": "16.799999", "Close": "16.799999", "Symbol": "GBT"}, {"Volume": "172000", "Open": "16.049999", "High": "16.299999", "Low": "15.90", "Date": "2017-02-06", "Adj_Close": "16.200001", "Close": "16.200001", "Symbol": "GBT"}, {"Volume": "183800", "Open": "16.25", "High": "16.35", "Low": "15.75", "Date": "2017-02-03", "Adj_Close": "16.10", "Close": "16.10", "Symbol": "GBT"}, {"Volume": "212300", "Open": "16.10", "High": "16.40", "Low": "15.70", "Date": "2017-02-02", "Adj_Close": "16.15", "Close": "16.15", "Symbol": "GBT"}, {"Volume": "262000", "Open": "16.15", "High": "16.25", "Low": "15.85", "Date": "2017-02-01", "Adj_Close": "16.10", "Close": "16.10", "Symbol": "GBT"}, {"Volume": "494900", "Open": "14.85", "High": "16.35", "Low": "14.70", "Date": "2017-01-31", "Adj_Close": "16.15", "Close": "16.15", "Symbol": "GBT"}, {"Volume": "637700", "Open": "15.90", "High": "16.00", "Low": "14.90", "Date": "2017-01-30", "Adj_Close": "14.95", "Close": "14.95", "Symbol": "GBT"}, {"Volume": "233800", "Open": "15.80", "High": "16.200001", "Low": "15.75", "Date": "2017-01-27", "Adj_Close": "16.00", "Close": "16.00", "Symbol": "GBT"}, {"Volume": "196300", "Open": "16.50", "High": "16.65", "Low": "15.85", "Date": "2017-01-26", "Adj_Close": "15.95", "Close": "15.95", "Symbol": "GBT"}, {"Volume": "205900", "Open": "16.700001", "High": "16.799999", "Low": "16.35", "Date": "2017-01-25", "Adj_Close": "16.450001", "Close": "16.450001", "Symbol": "GBT"}, {"Volume": "536000", "Open": "16.450001", "High": "16.65", "Low": "15.80", "Date": "2017-01-24", "Adj_Close": "16.60", "Close": "16.60", "Symbol": "GBT"}, {"Volume": "195500", "Open": "16.65", "High": "16.75", "Low": "16.200001", "Date": "2017-01-23", "Adj_Close": "16.450001", "Close": "16.450001", "Symbol": "GBT"}, {"Volume": "269500", "Open": "16.75", "High": "16.85", "Low": "16.50", "Date": "2017-01-20", "Adj_Close": "16.75", "Close": "16.75", "Symbol": "GBT"}, {"Volume": "334400", "Open": "16.75", "High": "16.75", "Low": "16.25", "Date": "2017-01-19", "Adj_Close": "16.65", "Close": "16.65", "Symbol": "GBT"}, {"Volume": "387600", "Open": "16.299999", "High": "16.799999", "Low": "16.25", "Date": "2017-01-18", "Adj_Close": "16.75", "Close": "16.75", "Symbol": "GBT"}, {"Volume": "395100", "Open": "16.65", "High": "16.65", "Low": "15.90", "Date": "2017-01-17", "Adj_Close": "16.40", "Close": "16.40", "Symbol": "GBT"}, {"Volume": "331400", "Open": "16.450001", "High": "16.799999", "Low": "16.40", "Date": "2017-01-13", "Adj_Close": "16.700001", "Close": "16.700001", "Symbol": "GBT"}, {"Volume": "226100", "Open": "16.200001", "High": "16.75", "Low": "16.049999", "Date": "2017-01-12", "Adj_Close": "16.450001", "Close": "16.450001", "Symbol": "GBT"}, {"Volume": "343100", "Open": "16.299999", "High": "16.65", "Low": "15.75", "Date": "2017-01-11", "Adj_Close": "16.35", "Close": "16.35", "Symbol": "GBT"}, {"Volume": "378800", "Open": "16.50", "High": "16.549999", "Low": "15.70", "Date": "2017-01-10", "Adj_Close": "16.40", "Close": "16.40", "Symbol": "GBT"}, {"Volume": "312900", "Open": "16.700001", "High": "16.90", "Low": "16.245001", "Date": "2017-01-09", "Adj_Close": "16.450001", "Close": "16.450001", "Symbol": "GBT"}, {"Volume": "406100", "Open": "16.40", "High": "16.549999", "Low": "15.80", "Date": "2017-01-06", "Adj_Close": "16.450001", "Close": "16.450001", "Symbol": "GBT"}, {"Volume": "600800", "Open": "16.00", "High": "16.549999", "Low": "15.80", "Date": "2017-01-05", "Adj_Close": "16.25", "Close": "16.25", "Symbol": "GBT"}, {"Volume": "1282700", "Open": "15.10", "High": "16.25", "Low": "14.70", "Date": "2017-01-04", "Adj_Close": "15.85", "Close": "15.85", "Symbol": "GBT"}, {"Volume": "319000", "Open": "14.70", "High": "14.95", "Low": "14.00", "Date": "2017-01-03", "Adj_Close": "14.30", "Close": "14.30", "Symbol": "GBT"}, {"Volume": "499100", "Open": "13.80", "High": "14.50", "Low": "13.60", "Date": "2016-12-30", "Adj_Close": "14.45", "Close": "14.45", "Symbol": "GBT"}, {"Volume": "521800", "Open": "13.95", "High": "14.15", "Low": "13.35", "Date": "2016-12-29", "Adj_Close": "13.90", "Close": "13.90", "Symbol": "GBT"}, {"Volume": "448900", "Open": "14.60", "High": "14.80", "Low": "13.70", "Date": "2016-12-28", "Adj_Close": "13.95", "Close": "13.95", "Symbol": "GBT"}, {"Volume": "404300", "Open": "15.20", "High": "15.25", "Low": "14.25", "Date": "2016-12-27", "Adj_Close": "14.50", "Close": "14.50", "Symbol": "GBT"}, {"Volume": "400400", "Open": "14.45", "High": "15.45", "Low": "14.45", "Date": "2016-12-23", "Adj_Close": "15.15", "Close": "15.15", "Symbol": "GBT"}, {"Volume": "533400", "Open": "15.20", "High": "15.30", "Low": "14.35", "Date": "2016-12-22", "Adj_Close": "14.45", "Close": "14.45", "Symbol": "GBT"}, {"Volume": "445300", "Open": "16.299999", "High": "16.299999", "Low": "15.00", "Date": "2016-12-21", "Adj_Close": "15.15", "Close": "15.15", "Symbol": "GBT"}, {"Volume": "199600", "Open": "16.200001", "High": "16.700001", "Low": "15.95", "Date": "2016-12-20", "Adj_Close": "16.200001", "Close": "16.200001", "Symbol": "GBT"}, {"Volume": "308100", "Open": "16.299999", "High": "16.75", "Low": "16.025", "Date": "2016-12-19", "Adj_Close": "16.10", "Close": "16.10", "Symbol": "GBT"}, {"Volume": "2028300", "Open": "16.299999", "High": "16.799999", "Low": "15.90", "Date": "2016-12-16", "Adj_Close": "16.25", "Close": "16.25", "Symbol": "GBT"}, {"Volume": "907600", "Open": "15.75", "High": "16.475", "Low": "15.50", "Date": "2016-12-15", "Adj_Close": "16.40", "Close": "16.40", "Symbol": "GBT"}, {"Volume": "864200", "Open": "16.950001", "High": "17.200001", "Low": "16.00", "Date": "2016-12-14", "Adj_Close": "16.10", "Close": "16.10", "Symbol": "GBT"}, {"Volume": "1001100", "Open": "16.700001", "High": "17.549999", "Low": "16.40", "Date": "2016-12-13", "Adj_Close": "17.00", "Close": "17.00", "Symbol": "GBT"}, {"Volume": "592500", "Open": "16.35", "High": "16.85", "Low": "16.00", "Date": "2016-12-12", "Adj_Close": "16.549999", "Close": "16.549999", "Symbol": "GBT"}, {"Volume": "441700", "Open": "16.450001", "High": "16.65", "Low": "16.10", "Date": "2016-12-09", "Adj_Close": "16.25", "Close": "16.25", "Symbol": "GBT"}, {"Volume": "847900", "Open": "15.80", "High": "16.549999", "Low": "15.50", "Date": "2016-12-08", "Adj_Close": "16.25", "Close": "16.25", "Symbol": "GBT"}, {"Volume": "573300", "Open": "16.049999", "High": "16.40", "Low": "15.55", "Date": "2016-12-07", "Adj_Close": "15.95", "Close": "15.95", "Symbol": "GBT"}, {"Volume": "1921500", "Open": "17.049999", "High": "17.25", "Low": "15.30", "Date": "2016-12-06", "Adj_Close": "16.40", "Close": "16.40", "Symbol": "GBT"}, {"Volume": "1634600", "Open": "20.15", "High": "20.290001", "Low": "17.049999", "Date": "2016-12-05", "Adj_Close": "17.25", "Close": "17.25", "Symbol": "GBT"}, {"Volume": "270900", "Open": "19.049999", "High": "19.60", "Low": "18.75", "Date": "2016-12-02", "Adj_Close": "19.10", "Close": "19.10", "Symbol": "GBT"}, {"Volume": "482400", "Open": "19.25", "High": "19.35", "Low": "18.50", "Date": "2016-12-01", "Adj_Close": "19.200001", "Close": "19.200001", "Symbol": "GBT"}, {"Volume": "487600", "Open": "19.200001", "High": "19.549999", "Low": "18.91", "Date": "2016-11-30", "Adj_Close": "19.15", "Close": "19.15", "Symbol": "GBT"}, {"Volume": "242400", "Open": "18.15", "High": "18.90", "Low": "17.872999", "Date": "2016-11-29", "Adj_Close": "18.65", "Close": "18.65", "Symbol": "GBT"}, {"Volume": "411000", "Open": "18.049999", "High": "18.50", "Low": "17.65", "Date": "2016-11-28", "Adj_Close": "18.049999", "Close": "18.049999", "Symbol": "GBT"}, {"Volume": "175600", "Open": "17.799999", "High": "18.65", "Low": "17.50", "Date": "2016-11-25", "Adj_Close": "18.549999", "Close": "18.549999", "Symbol": "GBT"}, {"Volume": "344200", "Open": "16.90", "High": "17.799999", "Low": "16.50", "Date": "2016-11-23", "Adj_Close": "17.700001", "Close": "17.700001", "Symbol": "GBT"}, {"Volume": "400200", "Open": "17.90", "High": "18.10", "Low": "17.049999", "Date": "2016-11-22", "Adj_Close": "17.15", "Close": "17.15", "Symbol": "GBT"}, {"Volume": "301100", "Open": "17.65", "High": "18.10", "Low": "17.40", "Date": "2016-11-21", "Adj_Close": "17.799999", "Close": "17.799999", "Symbol": "GBT"}, {"Volume": "644100", "Open": "17.60", "High": "17.695", "Low": "17.25", "Date": "2016-11-18", "Adj_Close": "17.549999", "Close": "17.549999", "Symbol": "GBT"}, {"Volume": "404700", "Open": "18.299999", "High": "18.768", "Low": "17.35", "Date": "2016-11-17", "Adj_Close": "17.549999", "Close": "17.549999", "Symbol": "GBT"}, {"Volume": "735400", "Open": "19.299999", "High": "19.799999", "Low": "18.10", "Date": "2016-11-16", "Adj_Close": "18.25", "Close": "18.25", "Symbol": "GBT"}, {"Volume": "751200", "Open": "20.40", "High": "20.450001", "Low": "19.049999", "Date": "2016-11-15", "Adj_Close": "19.50", "Close": "19.50", "Symbol": "GBT"}, {"Volume": "495700", "Open": "19.450001", "High": "20.799999", "Low": "19.299999", "Date": "2016-11-14", "Adj_Close": "20.700001", "Close": "20.700001", "Symbol": "GBT"}, {"Volume": "697700", "Open": "18.75", "High": "19.60", "Low": "18.40", "Date": "2016-11-11", "Adj_Close": "19.549999", "Close": "19.549999", "Symbol": "GBT"}, {"Volume": "1211100", "Open": "17.700001", "High": "19.59", "Low": "17.00", "Date": "2016-11-10", "Adj_Close": "18.75", "Close": "18.75", "Symbol": "GBT"}, {"Volume": "873900", "Open": "16.75", "High": "17.50", "Low": "16.75", "Date": "2016-11-09", "Adj_Close": "17.50", "Close": "17.50", "Symbol": "GBT"}, {"Volume": "295200", "Open": "16.450001", "High": "16.950001", "Low": "16.25", "Date": "2016-11-08", "Adj_Close": "16.25", "Close": "16.25", "Symbol": "GBT"}, {"Volume": "404000", "Open": "17.049999", "High": "17.299999", "Low": "16.200001", "Date": "2016-11-07", "Adj_Close": "16.60", "Close": "16.60", "Symbol": "GBT"}, {"Volume": "939500", "Open": "14.80", "High": "16.85", "Low": "14.80", "Date": "2016-11-04", "Adj_Close": "16.700001", "Close": "16.700001", "Symbol": "GBT"}, {"Volume": "1559800", "Open": "17.85", "High": "18.25", "Low": "15.10", "Date": "2016-11-03", "Adj_Close": "15.15", "Close": "15.15", "Symbol": "GBT"}, {"Volume": "1492500", "Open": "18.200001", "High": "19.00", "Low": "17.35", "Date": "2016-11-02", "Adj_Close": "17.65", "Close": "17.65", "Symbol": "GBT"}, {"Volume": "1617100", "Open": "18.15", "High": "18.75", "Low": "17.10", "Date": "2016-11-01", "Adj_Close": "18.15", "Close": "18.15", "Symbol": "GBT"}, {"Volume": "395000", "Open": "17.700001", "High": "17.700001", "Low": "16.65", "Date": "2016-10-31", "Adj_Close": "17.450001", "Close": "17.450001", "Symbol": "GBT"}, {"Volume": "503200", "Open": "18.50", "High": "18.625", "Low": "17.60", "Date": "2016-10-28", "Adj_Close": "17.65", "Close": "17.65", "Symbol": "GBT"}, {"Volume": "435900", "Open": "19.549999", "High": "19.950001", "Low": "18.50", "Date": "2016-10-27", "Adj_Close": "18.60", "Close": "18.60", "Symbol": "GBT"}, {"Volume": "580900", "Open": "19.65", "High": "19.915001", "Low": "19.00", "Date": "2016-10-26", "Adj_Close": "19.35", "Close": "19.35", "Symbol": "GBT"}, {"Volume": "2579200", "Open": "20.75", "High": "21.65", "Low": "19.25", "Date": "2016-10-25", "Adj_Close": "19.75", "Close": "19.75", "Symbol": "GBT"}, {"Volume": "326900", "Open": "18.950001", "High": "18.950001", "Low": "17.700001", "Date": "2016-10-24", "Adj_Close": "17.75", "Close": "17.75", "Symbol": "GBT"}, {"Volume": "332900", "Open": "18.50", "High": "19.10", "Low": "18.469999", "Date": "2016-10-21", "Adj_Close": "18.85", "Close": "18.85", "Symbol": "GBT"}, {"Volume": "276400", "Open": "18.00", "High": "18.875", "Low": "17.950001", "Date": "2016-10-20", "Adj_Close": "18.700001", "Close": "18.700001", "Symbol": "GBT"}, {"Volume": "293400", "Open": "18.299999", "High": "18.450001", "Low": "17.700001", "Date": "2016-10-19", "Adj_Close": "18.049999", "Close": "18.049999", "Symbol": "GBT"}, {"Volume": "185200", "Open": "17.65", "High": "18.25", "Low": "17.299999", "Date": "2016-10-18", "Adj_Close": "18.15", "Close": "18.15", "Symbol": "GBT"}, {"Volume": "293700", "Open": "17.450001", "High": "17.700001", "Low": "16.90", "Date": "2016-10-17", "Adj_Close": "17.25", "Close": "17.25", "Symbol": "GBT"}, {"Volume": "397200", "Open": "18.10", "High": "18.105", "Low": "16.805", "Date": "2016-10-14", "Adj_Close": "17.50", "Close": "17.50", "Symbol": "GBT"}, {"Volume": "320800", "Open": "17.450001", "High": "18.25", "Low": "17.105", "Date": "2016-10-13", "Adj_Close": "18.200001", "Close": "18.200001", "Symbol": "GBT"}, {"Volume": "355200", "Open": "18.15", "High": "18.65", "Low": "17.35", "Date": "2016-10-12", "Adj_Close": "17.60", "Close": "17.60", "Symbol": "GBT"}, {"Volume": "435000", "Open": "18.50", "High": "18.65", "Low": "17.549999", "Date": "2016-10-11", "Adj_Close": "18.25", "Close": "18.25", "Symbol": "GBT"}, {"Volume": "341100", "Open": "18.90", "High": "19.10", "Low": "18.35", "Date": "2016-10-10", "Adj_Close": "18.60", "Close": "18.60", "Symbol": "GBT"}, {"Volume": "547900", "Open": "18.700001", "High": "19.200001", "Low": "17.85", "Date": "2016-10-07", "Adj_Close": "18.50", "Close": "18.50", "Symbol": "GBT"}, {"Volume": "1158500", "Open": "19.299999", "High": "19.85", "Low": "17.549999", "Date": "2016-10-06", "Adj_Close": "18.799999", "Close": "18.799999", "Symbol": "GBT"}, {"Volume": "1884900", "Open": "22.85", "High": "23.25", "Low": "18.799999", "Date": "2016-10-05", "Adj_Close": "19.60", "Close": "19.60", "Symbol": "GBT"}, {"Volume": "344600", "Open": "22.40", "High": "23.15", "Low": "21.799999", "Date": "2016-10-04", "Adj_Close": "22.50", "Close": "22.50", "Symbol": "GBT"}, {"Volume": "415600", "Open": "23.25", "High": "23.799999", "Low": "21.35", "Date": "2016-10-03", "Adj_Close": "22.299999", "Close": "22.299999", "Symbol": "GBT"}, {"Volume": "1445900", "Open": "22.389999", "High": "23.24", "Low": "21.65", "Date": "2016-09-30", "Adj_Close": "23.049999", "Close": "23.049999", "Symbol": "GBT"}, {"Volume": "272500", "Open": "21.77", "High": "21.790001", "Low": "20.25", "Date": "2016-09-29", "Adj_Close": "20.459999", "Close": "20.459999", "Symbol": "GBT"}, {"Volume": "198000", "Open": "22.17", "High": "22.17", "Low": "21.160999", "Date": "2016-09-28", "Adj_Close": "21.83", "Close": "21.83", "Symbol": "GBT"}, {"Volume": "304400", "Open": "21.93", "High": "22.09", "Low": "21.120001", "Date": "2016-09-27", "Adj_Close": "22.02", "Close": "22.02", "Symbol": "GBT"}, {"Volume": "190200", "Open": "22.530001", "High": "22.530001", "Low": "21.809999", "Date": "2016-09-26", "Adj_Close": "21.950001", "Close": "21.950001", "Symbol": "GBT"}, {"Volume": "366200", "Open": "23.360001", "High": "24.10", "Low": "22.639999", "Date": "2016-09-23", "Adj_Close": "22.75", "Close": "22.75", "Symbol": "GBT"}, {"Volume": "407900", "Open": "23.709999", "High": "23.709999", "Low": "22.629999", "Date": "2016-09-22", "Adj_Close": "23.41", "Close": "23.41", "Symbol": "GBT"}, {"Volume": "582000", "Open": "22.92", "High": "23.879999", "Low": "22.83", "Date": "2016-09-21", "Adj_Close": "23.50", "Close": "23.50", "Symbol": "GBT"}, {"Volume": "981200", "Open": "23.559999", "High": "23.76", "Low": "21.65", "Date": "2016-09-20", "Adj_Close": "22.860001", "Close": "22.860001", "Symbol": "GBT"}, {"Volume": "597800", "Open": "22.50", "High": "23.65", "Low": "22.200001", "Date": "2016-09-19", "Adj_Close": "22.889999", "Close": "22.889999", "Symbol": "GBT"}, {"Volume": "698100", "Open": "20.309999", "High": "22.76", "Low": "20.209999", "Date": "2016-09-16", "Adj_Close": "22.57", "Close": "22.57", "Symbol": "GBT"}, {"Volume": "446900", "Open": "20.65", "High": "20.83", "Low": "20.030001", "Date": "2016-09-15", "Adj_Close": "20.469999", "Close": "20.469999", "Symbol": "GBT"}, {"Volume": "1448300", "Open": "18.93", "High": "21.42", "Low": "18.611", "Date": "2016-09-14", "Adj_Close": "20.540001", "Close": "20.540001", "Symbol": "GBT"}, {"Volume": "199400", "Open": "18.90", "High": "19.09", "Low": "18.209999", "Date": "2016-09-13", "Adj_Close": "18.469999", "Close": "18.469999", "Symbol": "GBT"}, {"Volume": "273500", "Open": "18.450001", "High": "19.33", "Low": "18.309999", "Date": "2016-09-12", "Adj_Close": "19.27", "Close": "19.27", "Symbol": "GBT"}, {"Volume": "527100", "Open": "19.67", "High": "19.90", "Low": "18.52", "Date": "2016-09-09", "Adj_Close": "18.58", "Close": "18.58", "Symbol": "GBT"}, {"Volume": "339200", "Open": "18.83", "High": "20.00", "Low": "18.700001", "Date": "2016-09-08", "Adj_Close": "19.889999", "Close": "19.889999", "Symbol": "GBT"}, {"Volume": "435300", "Open": "17.82", "High": "18.92", "Low": "17.82", "Date": "2016-09-07", "Adj_Close": "18.84", "Close": "18.84", "Symbol": "GBT"}, {"Volume": "129300", "Open": "17.57", "High": "18.02", "Low": "17.42", "Date": "2016-09-06", "Adj_Close": "17.85", "Close": "17.85", "Symbol": "GBT"}, {"Volume": "147200", "Open": "17.41", "High": "17.91", "Low": "17.059999", "Date": "2016-09-02", "Adj_Close": "17.450001", "Close": "17.450001", "Symbol": "GBT"}, {"Volume": "217200", "Open": "17.110001", "High": "17.360001", "Low": "16.90", "Date": "2016-09-01", "Adj_Close": "17.280001", "Close": "17.280001", "Symbol": "GBT"}, {"Volume": "225100", "Open": "18.24", "High": "18.24", "Low": "16.90", "Date": "2016-08-31", "Adj_Close": "16.99", "Close": "16.99", "Symbol": "GBT"}, {"Volume": "213000", "Open": "18.299999", "High": "18.549999", "Low": "18.07", "Date": "2016-08-30", "Adj_Close": "18.23", "Close": "18.23", "Symbol": "GBT"}, {"Volume": "121000", "Open": "18.35", "High": "18.59", "Low": "18.00", "Date": "2016-08-29", "Adj_Close": "18.17", "Close": "18.17", "Symbol": "GBT"}, {"Volume": "149700", "Open": "18.049999", "High": "18.65", "Low": "18.00", "Date": "2016-08-26", "Adj_Close": "18.280001", "Close": "18.280001", "Symbol": "GBT"}, {"Volume": "599400", "Open": "18.50", "High": "19.629999", "Low": "17.780001", "Date": "2016-08-25", "Adj_Close": "18.049999", "Close": "18.049999", "Symbol": "GBT"}, {"Volume": "255800", "Open": "19.440001", "High": "19.92", "Low": "18.18", "Date": "2016-08-24", "Adj_Close": "18.42", "Close": "18.42", "Symbol": "GBT"}, {"Volume": "195800", "Open": "19.559999", "High": "19.77", "Low": "19.139999", "Date": "2016-08-23", "Adj_Close": "19.379999", "Close": "19.379999", "Symbol": "GBT"}, {"Volume": "146500", "Open": "19.719999", "High": "19.92", "Low": "19.26", "Date": "2016-08-22", "Adj_Close": "19.48", "Close": "19.48", "Symbol": "GBT"}, {"Volume": "363900", "Open": "19.870001", "High": "20.15", "Low": "19.24", "Date": "2016-08-19", "Adj_Close": "19.540001", "Close": "19.540001", "Symbol": "GBT"}, {"Volume": "317400", "Open": "19.50", "High": "20.15", "Low": "19.33", "Date": "2016-08-18", "Adj_Close": "20.00", "Close": "20.00", "Symbol": "GBT"}, {"Volume": "566100", "Open": "21.65", "High": "21.65", "Low": "19.33", "Date": "2016-08-17", "Adj_Close": "19.52", "Close": "19.52", "Symbol": "GBT"}, {"Volume": "452000", "Open": "21.50", "High": "22.280001", "Low": "21.120001", "Date": "2016-08-16", "Adj_Close": "21.389999", "Close": "21.389999", "Symbol": "GBT"}, {"Volume": "369300", "Open": "21.91", "High": "22.219999", "Low": "21.27", "Date": "2016-08-15", "Adj_Close": "22.00", "Close": "22.00", "Symbol": "GBT"}, {"Volume": "1136800", "Open": "18.66", "High": "21.969", "Low": "18.66", "Date": "2016-08-12", "Adj_Close": "21.950001", "Close": "21.950001", "Symbol": "GBT"}, {"Volume": "335600", "Open": "17.790001", "High": "18.83", "Low": "17.51", "Date": "2016-08-11", "Adj_Close": "18.639999", "Close": "18.639999", "Symbol": "GBT"}, {"Volume": "177900", "Open": "17.959999", "High": "18.280001", "Low": "17.482", "Date": "2016-08-10", "Adj_Close": "17.530001", "Close": "17.530001", "Symbol": "GBT"}, {"Volume": "148000", "Open": "17.950001", "High": "18.17", "Low": "17.66", "Date": "2016-08-09", "Adj_Close": "17.98", "Close": "17.98", "Symbol": "GBT"}, {"Volume": "109200", "Open": "18.18", "High": "18.365", "Low": "17.780001", "Date": "2016-08-08", "Adj_Close": "17.85", "Close": "17.85", "Symbol": "GBT"}, {"Volume": "255000", "Open": "18.610001", "High": "18.610001", "Low": "18.120001", "Date": "2016-08-05", "Adj_Close": "18.18", "Close": "18.18", "Symbol": "GBT"}, {"Volume": "281000", "Open": "17.879999", "High": "18.799999", "Low": "17.879999", "Date": "2016-08-04", "Adj_Close": "18.450001", "Close": "18.450001", "Symbol": "GBT"}, {"Volume": "253200", "Open": "17.75", "High": "18.24", "Low": "17.370001", "Date": "2016-08-03", "Adj_Close": "18.129999", "Close": "18.129999", "Symbol": "GBT"}, {"Volume": "203700", "Open": "17.65", "High": "18.08", "Low": "17.115", "Date": "2016-08-02", "Adj_Close": "17.889999", "Close": "17.889999", "Symbol": "GBT"}, {"Volume": "211700", "Open": "17.93", "High": "18.209999", "Low": "17.48", "Date": "2016-08-01", "Adj_Close": "17.700001", "Close": "17.700001", "Symbol": "GBT"}, {"Volume": "452300", "Open": "17.540001", "High": "18.049999", "Low": "17.389999", "Date": "2016-07-29", "Adj_Close": "17.879999", "Close": "17.879999", "Symbol": "GBT"}, {"Volume": "170900", "Open": "17.799999", "High": "18.18", "Low": "17.370001", "Date": "2016-07-28", "Adj_Close": "17.610001", "Close": "17.610001", "Symbol": "GBT"}, {"Volume": "276800", "Open": "17.139999", "High": "17.889999", "Low": "17.083", "Date": "2016-07-27", "Adj_Close": "17.860001", "Close": "17.860001", "Symbol": "GBT"}, {"Volume": "230500", "Open": "17.219999", "High": "17.389999", "Low": "16.90", "Date": "2016-07-26", "Adj_Close": "17.049999", "Close": "17.049999", "Symbol": "GBT"}, {"Volume": "298700", "Open": "17.959999", "High": "17.959999", "Low": "16.91", "Date": "2016-07-25", "Adj_Close": "17.219999", "Close": "17.219999", "Symbol": "GBT"}, {"Volume": "150700", "Open": "18.280001", "High": "18.280001", "Low": "17.809999", "Date": "2016-07-22", "Adj_Close": "17.950001", "Close": "17.950001", "Symbol": "GBT"}, {"Volume": "361100", "Open": "18.75", "High": "18.790001", "Low": "18.139999", "Date": "2016-07-21", "Adj_Close": "18.35", "Close": "18.35", "Symbol": "GBT"}, {"Volume": "425800", "Open": "18.639999", "High": "18.719999", "Low": "18.309999", "Date": "2016-07-20", "Adj_Close": "18.610001", "Close": "18.610001", "Symbol": "GBT"}, {"Volume": "998900", "Open": "18.059999", "High": "18.60", "Low": "17.940001", "Date": "2016-07-19", "Adj_Close": "18.549999", "Close": "18.549999", "Symbol": "GBT"}, {"Volume": "752800", "Open": "16.620001", "High": "17.969999", "Low": "16.58", "Date": "2016-07-18", "Adj_Close": "17.959999", "Close": "17.959999", "Symbol": "GBT"}, {"Volume": "291300", "Open": "16.549999", "High": "16.620001", "Low": "16.299999", "Date": "2016-07-15", "Adj_Close": "16.52", "Close": "16.52", "Symbol": "GBT"}, {"Volume": "269900", "Open": "17.309999", "High": "17.33", "Low": "16.43", "Date": "2016-07-14", "Adj_Close": "16.51", "Close": "16.51", "Symbol": "GBT"}, {"Volume": "506300", "Open": "18.120001", "High": "18.24", "Low": "17.190001", "Date": "2016-07-13", "Adj_Close": "17.23", "Close": "17.23", "Symbol": "GBT"}, {"Volume": "269000", "Open": "17.68", "High": "18.120001", "Low": "17.540001", "Date": "2016-07-12", "Adj_Close": "18.00", "Close": "18.00", "Symbol": "GBT"}, {"Volume": "217700", "Open": "17.690001", "High": "17.940001", "Low": "17.379999", "Date": "2016-07-11", "Adj_Close": "17.51", "Close": "17.51", "Symbol": "GBT"}, {"Volume": "349400", "Open": "17.209999", "High": "17.74", "Low": "17.08", "Date": "2016-07-08", "Adj_Close": "17.620001", "Close": "17.620001", "Symbol": "GBT"}, {"Volume": "241400", "Open": "16.65", "High": "17.219999", "Low": "16.514999", "Date": "2016-07-07", "Adj_Close": "17.059999", "Close": "17.059999", "Symbol": "GBT"}, {"Volume": "276100", "Open": "16.48", "High": "16.98", "Low": "16.07", "Date": "2016-07-06", "Adj_Close": "16.629999", "Close": "16.629999", "Symbol": "GBT"}, {"Volume": "289300", "Open": "17.24", "High": "17.24", "Low": "16.33", "Date": "2016-07-05", "Adj_Close": "16.66", "Close": "16.66", "Symbol": "GBT"}, {"Volume": "1226700", "Open": "16.42", "High": "17.75", "Low": "16.42", "Date": "2016-07-01", "Adj_Close": "17.370001", "Close": "17.370001", "Symbol": "GBT"}, {"Volume": "683000", "Open": "15.96", "High": "16.849001", "Low": "15.80", "Date": "2016-06-30", "Adj_Close": "16.59", "Close": "16.59", "Symbol": "GBT"}, {"Volume": "635100", "Open": "16.02", "High": "16.450001", "Low": "15.64", "Date": "2016-06-29", "Adj_Close": "16.10", "Close": "16.10", "Symbol": "GBT"}, {"Volume": "895600", "Open": "14.99", "High": "16.110001", "Low": "14.95", "Date": "2016-06-28", "Adj_Close": "15.68", "Close": "15.68", "Symbol": "GBT"}, {"Volume": "1282600", "Open": "15.64", "High": "15.69", "Low": "14.22", "Date": "2016-06-27", "Adj_Close": "14.70", "Close": "14.70", "Symbol": "GBT"}, {"Volume": "1761100", "Open": "15.99", "High": "17.00", "Low": "15.62", "Date": "2016-06-24", "Adj_Close": "15.69", "Close": "15.69", "Symbol": "GBT"}, {"Volume": "1159500", "Open": "17.68", "High": "17.90", "Low": "16.50", "Date": "2016-06-23", "Adj_Close": "16.74", "Close": "16.74", "Symbol": "GBT"}, {"Volume": "2223300", "Open": "17.709999", "High": "18.08", "Low": "16.809999", "Date": "2016-06-22", "Adj_Close": "17.559999", "Close": "17.559999", "Symbol": "GBT"}, {"Volume": "7342500", "Open": "19.889999", "High": "20.139999", "Low": "17.42", "Date": "2016-06-21", "Adj_Close": "17.799999", "Close": "17.799999", "Symbol": "GBT"}, {"Volume": "1266800", "Open": "17.610001", "High": "19.912001", "Low": "17.60", "Date": "2016-06-20", "Adj_Close": "18.940001", "Close": "18.940001", "Symbol": "GBT"}, {"Volume": "494000", "Open": "19.00", "High": "19.24", "Low": "17.76", "Date": "2016-06-17", "Adj_Close": "17.83", "Close": "17.83", "Symbol": "GBT"}, {"Volume": "907500", "Open": "19.41", "High": "19.41", "Low": "17.83", "Date": "2016-06-16", "Adj_Close": "18.85", "Close": "18.85", "Symbol": "GBT"}, {"Volume": "864900", "Open": "20.60", "High": "20.865999", "Low": "19.24", "Date": "2016-06-15", "Adj_Close": "19.50", "Close": "19.50", "Symbol": "GBT"}, {"Volume": "507600", "Open": "21.83", "High": "23.007", "Low": "21.042999", "Date": "2016-06-14", "Adj_Close": "21.10", "Close": "21.10", "Symbol": "GBT"}, {"Volume": "1106100", "Open": "23.50", "High": "23.620001", "Low": "21.10", "Date": "2016-06-13", "Adj_Close": "22.02", "Close": "22.02", "Symbol": "GBT"}, {"Volume": "4733200", "Open": "24.719999", "High": "27.99", "Low": "22.76", "Date": "2016-06-10", "Adj_Close": "24.15", "Close": "24.15", "Symbol": "GBT"}, {"Volume": "546000", "Open": "23.99", "High": "24.50", "Low": "22.02", "Date": "2016-06-09", "Adj_Close": "22.15", "Close": "22.15", "Symbol": "GBT"}, {"Volume": "266100", "Open": "24.559999", "High": "24.610001", "Low": "23.16", "Date": "2016-06-08", "Adj_Close": "24.129999", "Close": "24.129999", "Symbol": "GBT"}, {"Volume": "277900", "Open": "25.620001", "High": "25.90", "Low": "24.299999", "Date": "2016-06-07", "Adj_Close": "24.360001", "Close": "24.360001", "Symbol": "GBT"}, {"Volume": "186200", "Open": "25.959999", "High": "26.549999", "Low": "25.280001", "Date": "2016-06-06", "Adj_Close": "25.90", "Close": "25.90", "Symbol": "GBT"}, {"Volume": "303000", "Open": "26.290001", "High": "26.65", "Low": "25.082001", "Date": "2016-06-03", "Adj_Close": "25.950001", "Close": "25.950001", "Symbol": "GBT"}, {"Volume": "470000", "Open": "23.74", "High": "26.559999", "Low": "23.629999", "Date": "2016-06-02", "Adj_Close": "26.49", "Close": "26.49", "Symbol": "GBT"}, {"Volume": "216700", "Open": "23.690001", "High": "24.00", "Low": "22.629999", "Date": "2016-06-01", "Adj_Close": "23.74", "Close": "23.74", "Symbol": "GBT"}, {"Volume": "277900", "Open": "23.41", "High": "23.959999", "Low": "23.17", "Date": "2016-05-31", "Adj_Close": "23.92", "Close": "23.92", "Symbol": "GBT"}, {"Volume": "158000", "Open": "22.280001", "High": "23.370001", "Low": "21.98", "Date": "2016-05-27", "Adj_Close": "23.16", "Close": "23.16", "Symbol": "GBT"}, {"Volume": "110500", "Open": "22.059999", "High": "22.50", "Low": "21.384001", "Date": "2016-05-26", "Adj_Close": "22.34", "Close": "22.34", "Symbol": "GBT"}, {"Volume": "258800", "Open": "21.540001", "High": "22.50", "Low": "21.309999", "Date": "2016-05-25", "Adj_Close": "22.18", "Close": "22.18", "Symbol": "GBT"}, {"Volume": "289800", "Open": "20.58", "High": "21.50", "Low": "20.18", "Date": "2016-05-24", "Adj_Close": "21.309999", "Close": "21.309999", "Symbol": "GBT"}, {"Volume": "99900", "Open": "20.690001", "High": "20.780001", "Low": "20.280001", "Date": "2016-05-23", "Adj_Close": "20.52", "Close": "20.52", "Symbol": "GBT"}, {"Volume": "199000", "Open": "20.620001", "High": "21.014999", "Low": "20.040001", "Date": "2016-05-20", "Adj_Close": "20.639999", "Close": "20.639999", "Symbol": "GBT"}, {"Volume": "607600", "Open": "19.16", "High": "20.780001", "Low": "19.030001", "Date": "2016-05-19", "Adj_Close": "20.73", "Close": "20.73", "Symbol": "GBT"}, {"Volume": "325500", "Open": "18.219999", "High": "19.389999", "Low": "18.209999", "Date": "2016-05-18", "Adj_Close": "19.26", "Close": "19.26", "Symbol": "GBT"}, {"Volume": "581800", "Open": "19.379999", "High": "19.40", "Low": "18.27", "Date": "2016-05-17", "Adj_Close": "18.34", "Close": "18.34", "Symbol": "GBT"}, {"Volume": "292700", "Open": "19.27", "High": "20.139999", "Low": "18.775", "Date": "2016-05-16", "Adj_Close": "19.41", "Close": "19.41", "Symbol": "GBT"}, {"Volume": "455200", "Open": "17.58", "High": "19.389999", "Low": "17.58", "Date": "2016-05-13", "Adj_Close": "19.26", "Close": "19.26", "Symbol": "GBT"}, {"Volume": "216400", "Open": "18.49", "High": "18.66", "Low": "17.23", "Date": "2016-05-12", "Adj_Close": "17.85", "Close": "17.85", "Symbol": "GBT"}, {"Volume": "214300", "Open": "18.951", "High": "19.25", "Low": "18.055", "Date": "2016-05-11", "Adj_Close": "18.33", "Close": "18.33", "Symbol": "GBT"}, {"Volume": "284300", "Open": "19.40", "High": "19.434999", "Low": "18.25", "Date": "2016-05-10", "Adj_Close": "18.92", "Close": "18.92", "Symbol": "GBT"}, {"Volume": "412300", "Open": "18.34", "High": "19.48", "Low": "18.01", "Date": "2016-05-09", "Adj_Close": "19.27", "Close": "19.27", "Symbol": "GBT"}, {"Volume": "320000", "Open": "18.59", "High": "19.120001", "Low": "17.91", "Date": "2016-05-06", "Adj_Close": "18.26", "Close": "18.26", "Symbol": "GBT"}, {"Volume": "556900", "Open": "19.75", "High": "19.75", "Low": "18.280001", "Date": "2016-05-05", "Adj_Close": "18.709999", "Close": "18.709999", "Symbol": "GBT"}, {"Volume": "236900", "Open": "20.690001", "High": "21.200001", "Low": "19.08", "Date": "2016-05-04", "Adj_Close": "19.98", "Close": "19.98", "Symbol": "GBT"}, {"Volume": "163300", "Open": "20.51", "High": "21.040001", "Low": "20.07", "Date": "2016-05-03", "Adj_Close": "21.01", "Close": "21.01", "Symbol": "GBT"}, {"Volume": "121600", "Open": "20.17", "High": "20.85", "Low": "19.950001", "Date": "2016-05-02", "Adj_Close": "20.799999", "Close": "20.799999", "Symbol": "GBT"}, {"Volume": "297900", "Open": "20.90", "High": "21.40", "Low": "19.33", "Date": "2016-04-29", "Adj_Close": "20.17", "Close": "20.17", "Symbol": "GBT"}, {"Volume": "289700", "Open": "20.950001", "High": "22.15", "Low": "20.26", "Date": "2016-04-28", "Adj_Close": "21.00", "Close": "21.00", "Symbol": "GBT"}, {"Volume": "191700", "Open": "20.32", "High": "21.379999", "Low": "19.99", "Date": "2016-04-27", "Adj_Close": "21.040001", "Close": "21.040001", "Symbol": "GBT"}, {"Volume": "151800", "Open": "21.299999", "High": "21.299999", "Low": "20.190001", "Date": "2016-04-26", "Adj_Close": "20.280001", "Close": "20.280001", "Symbol": "GBT"}, {"Volume": "140400", "Open": "21.32", "High": "21.860001", "Low": "20.940001", "Date": "2016-04-25", "Adj_Close": "21.24", "Close": "21.24", "Symbol": "GBT"}, {"Volume": "146800", "Open": "21.50", "High": "21.610001", "Low": "20.549999", "Date": "2016-04-22", "Adj_Close": "21.290001", "Close": "21.290001", "Symbol": "GBT"}, {"Volume": "294300", "Open": "20.76", "High": "21.49", "Low": "20.002001", "Date": "2016-04-21", "Adj_Close": "21.26", "Close": "21.26", "Symbol": "GBT"}, {"Volume": "506300", "Open": "21.129999", "High": "21.60", "Low": "20.25", "Date": "2016-04-20", "Adj_Close": "20.790001", "Close": "20.790001", "Symbol": "GBT"}, {"Volume": "220200", "Open": "21.07", "High": "21.290001", "Low": "19.82", "Date": "2016-04-19", "Adj_Close": "19.98", "Close": "19.98", "Symbol": "GBT"}, {"Volume": "153000", "Open": "21.120001", "High": "21.379999", "Low": "20.75", "Date": "2016-04-18", "Adj_Close": "21.110001", "Close": "21.110001", "Symbol": "GBT"}, {"Volume": "148500", "Open": "20.459999", "High": "21.530001", "Low": "20.129999", "Date": "2016-04-15", "Adj_Close": "21.360001", "Close": "21.360001", "Symbol": "GBT"}, {"Volume": "224200", "Open": "20.540001", "High": "20.84", "Low": "20.025", "Date": "2016-04-14", "Adj_Close": "20.51", "Close": "20.51", "Symbol": "GBT"}, {"Volume": "126600", "Open": "19.67", "High": "20.60", "Low": "19.385", "Date": "2016-04-13", "Adj_Close": "20.52", "Close": "20.52", "Symbol": "GBT"}, {"Volume": "161400", "Open": "19.07", "High": "19.66", "Low": "18.85", "Date": "2016-04-12", "Adj_Close": "19.43", "Close": "19.43", "Symbol": "GBT"}, {"Volume": "183500", "Open": "19.209999", "High": "19.77", "Low": "18.525", "Date": "2016-04-11", "Adj_Close": "19.059999", "Close": "19.059999", "Symbol": "GBT"}, {"Volume": "139800", "Open": "19.639999", "High": "19.85", "Low": "18.50", "Date": "2016-04-08", "Adj_Close": "19.00", "Close": "19.00", "Symbol": "GBT"}, {"Volume": "403000", "Open": "20.389999", "High": "21.25", "Low": "18.90", "Date": "2016-04-07", "Adj_Close": "19.25", "Close": "19.25", "Symbol": "GBT"}, {"Volume": "372300", "Open": "18.780001", "High": "20.934999", "Low": "18.389999", "Date": "2016-04-06", "Adj_Close": "20.76", "Close": "20.76", "Symbol": "GBT"}, {"Volume": "217000", "Open": "17.879999", "High": "19.370001", "Low": "17.690001", "Date": "2016-04-05", "Adj_Close": "18.68", "Close": "18.68", "Symbol": "GBT"}, {"Volume": "531000", "Open": "16.200001", "High": "18.625", "Low": "15.425", "Date": "2016-04-04", "Adj_Close": "18.139999", "Close": "18.139999", "Symbol": "GBT"}, {"Volume": "220100", "Open": "15.57", "High": "16.309999", "Low": "15.10", "Date": "2016-04-01", "Adj_Close": "16.129999", "Close": "16.129999", "Symbol": "GBT"}, {"Volume": "306700", "Open": "14.93", "High": "16.41", "Low": "14.78", "Date": "2016-03-31", "Adj_Close": "15.86", "Close": "15.86", "Symbol": "GBT"}, {"Volume": "159300", "Open": "14.71", "High": "15.16", "Low": "14.47", "Date": "2016-03-30", "Adj_Close": "14.97", "Close": "14.97", "Symbol": "GBT"}, {"Volume": "299900", "Open": "12.94", "High": "14.85", "Low": "12.24", "Date": "2016-03-29", "Adj_Close": "14.54", "Close": "14.54", "Symbol": "GBT"}, {"Volume": "341400", "Open": "14.23", "High": "14.637", "Low": "12.79", "Date": "2016-03-28", "Adj_Close": "12.99", "Close": "12.99", "Symbol": "GBT"}, {"Volume": "199600", "Open": "14.85", "High": "14.89", "Low": "13.86", "Date": "2016-03-24", "Adj_Close": "14.06", "Close": "14.06", "Symbol": "GBT"}, {"Volume": "314300", "Open": "16.049999", "High": "16.15", "Low": "14.87", "Date": "2016-03-23", "Adj_Close": "15.00", "Close": "15.00", "Symbol": "GBT"}, {"Volume": "208900", "Open": "15.61", "High": "16.540001", "Low": "15.57", "Date": "2016-03-22", "Adj_Close": "16.120001", "Close": "16.120001", "Symbol": "GBT"}, {"Volume": "119100", "Open": "15.58", "High": "16.08", "Low": "15.31", "Date": "2016-03-21", "Adj_Close": "15.83", "Close": "15.83", "Symbol": "GBT"}, {"Volume": "374800", "Open": "15.39", "High": "15.94", "Low": "14.81", "Date": "2016-03-18", "Adj_Close": "15.62", "Close": "15.62", "Symbol": "GBT"}, {"Volume": "172300", "Open": "15.98", "High": "16.040001", "Low": "15.19", "Date": "2016-03-17", "Adj_Close": "15.27", "Close": "15.27", "Symbol": "GBT"}, {"Volume": "164000", "Open": "15.69", "High": "16.110001", "Low": "15.51", "Date": "2016-03-16", "Adj_Close": "15.98", "Close": "15.98", "Symbol": "GBT"}, {"Volume": "237400", "Open": "16.51", "High": "17.23", "Low": "15.51", "Date": "2016-03-15", "Adj_Close": "15.77", "Close": "15.77", "Symbol": "GBT"}, {"Volume": "140700", "Open": "15.91", "High": "17.26", "Low": "15.83", "Date": "2016-03-14", "Adj_Close": "16.67", "Close": "16.67", "Symbol": "GBT"}, {"Volume": "195700", "Open": "15.29", "High": "16.49", "Low": "15.25", "Date": "2016-03-11", "Adj_Close": "16.02", "Close": "16.02", "Symbol": "GBT"}, {"Volume": "283600", "Open": "15.74", "High": "16.528999", "Low": "14.68", "Date": "2016-03-10", "Adj_Close": "15.06", "Close": "15.06", "Symbol": "GBT"}, {"Volume": "164900", "Open": "16.190001", "High": "16.459999", "Low": "15.36", "Date": "2016-03-09", "Adj_Close": "15.58", "Close": "15.58", "Symbol": "GBT"}, {"Volume": "245300", "Open": "17.50", "High": "17.620001", "Low": "15.80", "Date": "2016-03-08", "Adj_Close": "16.08", "Close": "16.08", "Symbol": "GBT"}, {"Volume": "240500", "Open": "16.41", "High": "17.700001", "Low": "16.26", "Date": "2016-03-07", "Adj_Close": "17.700001", "Close": "17.700001", "Symbol": "GBT"}, {"Volume": "433000", "Open": "16.059999", "High": "16.540001", "Low": "15.00", "Date": "2016-03-04", "Adj_Close": "16.450001", "Close": "16.450001", "Symbol": "GBT"}, {"Volume": "263000", "Open": "15.62", "High": "16.51", "Low": "15.61", "Date": "2016-03-03", "Adj_Close": "16.00", "Close": "16.00", "Symbol": "GBT"}, {"Volume": "316200", "Open": "14.76", "High": "15.98", "Low": "14.62", "Date": "2016-03-02", "Adj_Close": "15.57", "Close": "15.57", "Symbol": "GBT"}, {"Volume": "232300", "Open": "15.08", "High": "15.19", "Low": "14.63", "Date": "2016-03-01", "Adj_Close": "15.01", "Close": "15.01", "Symbol": "GBT"}, {"Volume": "196200", "Open": "14.88", "High": "15.35", "Low": "14.52", "Date": "2016-02-29", "Adj_Close": "14.93", "Close": "14.93", "Symbol": "GBT"}, {"Volume": "205200", "Open": "15.03", "High": "15.51", "Low": "14.55", "Date": "2016-02-26", "Adj_Close": "14.87", "Close": "14.87", "Symbol": "GBT"}, {"Volume": "294900", "Open": "15.10", "High": "15.94", "Low": "14.56", "Date": "2016-02-25", "Adj_Close": "14.93", "Close": "14.93", "Symbol": "GBT"}, {"Volume": "186300", "Open": "15.30", "High": "15.30", "Low": "14.784", "Date": "2016-02-24", "Adj_Close": "14.96", "Close": "14.96", "Symbol": "GBT"}, {"Volume": "278400", "Open": "16.049999", "High": "16.969999", "Low": "15.37", "Date": "2016-02-23", "Adj_Close": "15.53", "Close": "15.53", "Symbol": "GBT"}, {"Volume": "193700", "Open": "16.809999", "High": "17.200001", "Low": "16.26", "Date": "2016-02-22", "Adj_Close": "16.299999", "Close": "16.299999", "Symbol": "GBT"}, {"Volume": "192700", "Open": "17.059999", "High": "17.549999", "Low": "16.48", "Date": "2016-02-19", "Adj_Close": "16.700001", "Close": "16.700001", "Symbol": "GBT"}, {"Volume": "210700", "Open": "17.559999", "High": "17.65", "Low": "16.93", "Date": "2016-02-18", "Adj_Close": "17.15", "Close": "17.15", "Symbol": "GBT"}, {"Volume": "299700", "Open": "16.389999", "High": "18.040001", "Low": "16.389999", "Date": "2016-02-17", "Adj_Close": "17.469999", "Close": "17.469999", "Symbol": "GBT"}, {"Volume": "608400", "Open": "15.14", "High": "16.690001", "Low": "15.14", "Date": "2016-02-16", "Adj_Close": "16.17", "Close": "16.17", "Symbol": "GBT"}, {"Volume": "204000", "Open": "14.52", "High": "15.03", "Low": "14.21", "Date": "2016-02-12", "Adj_Close": "14.94", "Close": "14.94", "Symbol": "GBT"}, {"Volume": "343800", "Open": "13.39", "High": "14.43", "Low": "12.89", "Date": "2016-02-11", "Adj_Close": "14.36", "Close": "14.36", "Symbol": "GBT"}, {"Volume": "434600", "Open": "13.14", "High": "14.23", "Low": "12.69", "Date": "2016-02-10", "Adj_Close": "13.76", "Close": "13.76", "Symbol": "GBT"}, {"Volume": "403700", "Open": "14.70", "High": "15.50", "Low": "12.85", "Date": "2016-02-09", "Adj_Close": "12.95", "Close": "12.95", "Symbol": "GBT"}, {"Volume": "661700", "Open": "17.32", "High": "17.32", "Low": "14.72", "Date": "2016-02-08", "Adj_Close": "15.03", "Close": "15.03", "Symbol": "GBT"}, {"Volume": "231600", "Open": "19.32", "High": "19.32", "Low": "18.35", "Date": "2016-02-05", "Adj_Close": "18.58", "Close": "18.58", "Symbol": "GBT"}, {"Volume": "207900", "Open": "19.370001", "High": "20.07", "Low": "18.93", "Date": "2016-02-04", "Adj_Close": "19.549999", "Close": "19.549999", "Symbol": "GBT"}, {"Volume": "346700", "Open": "19.02", "High": "19.60", "Low": "17.709999", "Date": "2016-02-03", "Adj_Close": "19.530001", "Close": "19.530001", "Symbol": "GBT"}, {"Volume": "316300", "Open": "18.85", "High": "19.219999", "Low": "18.35", "Date": "2016-02-02", "Adj_Close": "18.780001", "Close": "18.780001", "Symbol": "GBT"}, {"Volume": "500700", "Open": "18.629999", "High": "19.620001", "Low": "16.99", "Date": "2016-02-01", "Adj_Close": "19.24", "Close": "19.24", "Symbol": "GBT"}, {"Volume": "215700", "Open": "19.25", "High": "19.450001", "Low": "18.16", "Date": "2016-01-29", "Adj_Close": "18.93", "Close": "18.93", "Symbol": "GBT"}, {"Volume": "345900", "Open": "19.879999", "High": "19.879999", "Low": "18.50", "Date": "2016-01-28", "Adj_Close": "19.32", "Close": "19.32", "Symbol": "GBT"}, {"Volume": "234600", "Open": "20.940001", "High": "20.940001", "Low": "19.41", "Date": "2016-01-27", "Adj_Close": "19.610001", "Close": "19.610001", "Symbol": "GBT"}, {"Volume": "312800", "Open": "19.620001", "High": "21.26", "Low": "19.469999", "Date": "2016-01-26", "Adj_Close": "20.940001", "Close": "20.940001", "Symbol": "GBT"}, {"Volume": "334400", "Open": "19.48", "High": "19.959999", "Low": "19.110001", "Date": "2016-01-25", "Adj_Close": "19.49", "Close": "19.49", "Symbol": "GBT"}, {"Volume": "329900", "Open": "19.780001", "High": "20.049", "Low": "19.040001", "Date": "2016-01-22", "Adj_Close": "19.50", "Close": "19.50", "Symbol": "GBT"}, {"Volume": "193900", "Open": "20.26", "High": "20.99", "Low": "19.16", "Date": "2016-01-21", "Adj_Close": "19.290001", "Close": "19.290001", "Symbol": "GBT"}, {"Volume": "339300", "Open": "19.85", "High": "20.969999", "Low": "18.40", "Date": "2016-01-20", "Adj_Close": "20.209999", "Close": "20.209999", "Symbol": "GBT"}, {"Volume": "293700", "Open": "21.74", "High": "21.74", "Low": "19.32", "Date": "2016-01-19", "Adj_Close": "20.290001", "Close": "20.290001", "Symbol": "GBT"}, {"Volume": "314700", "Open": "21.66", "High": "22.379999", "Low": "20.379999", "Date": "2016-01-15", "Adj_Close": "21.309999", "Close": "21.309999", "Symbol": "GBT"}, {"Volume": "965100", "Open": "21.10", "High": "26.77", "Low": "21.10", "Date": "2016-01-14", "Adj_Close": "22.870001", "Close": "22.870001", "Symbol": "GBT"}, {"Volume": "389800", "Open": "23.629999", "High": "23.73", "Low": "20.43", "Date": "2016-01-13", "Adj_Close": "21.32", "Close": "21.32", "Symbol": "GBT"}, {"Volume": "245900", "Open": "23.440001", "High": "23.75", "Low": "22.799999", "Date": "2016-01-12", "Adj_Close": "23.41", "Close": "23.41", "Symbol": "GBT"}, {"Volume": "643500", "Open": "23.889999", "High": "24.110001", "Low": "21.50", "Date": "2016-01-11", "Adj_Close": "23.34", "Close": "23.34", "Symbol": "GBT"}, {"Volume": "303700", "Open": "22.870001", "High": "23.860001", "Low": "22.389999", "Date": "2016-01-08", "Adj_Close": "23.40", "Close": "23.40", "Symbol": "GBT"}, {"Volume": "404300", "Open": "23.690001", "High": "23.933001", "Low": "21.700001", "Date": "2016-01-07", "Adj_Close": "22.459999", "Close": "22.459999", "Symbol": "GBT"}, {"Volume": "417000", "Open": "25.049999", "High": "25.059999", "Low": "23.24", "Date": "2016-01-06", "Adj_Close": "23.93", "Close": "23.93", "Symbol": "GBT"}, {"Volume": "440500", "Open": "29.26", "High": "29.629999", "Low": "26.41", "Date": "2016-01-05", "Adj_Close": "27.18", "Close": "27.18", "Symbol": "GBT"}, {"Volume": "200300", "Open": "31.780001", "High": "31.969999", "Low": "29.09", "Date": "2016-01-04", "Adj_Close": "29.209999", "Close": "29.209999", "Symbol": "GBT"}, {"Volume": "195900", "Open": "31.200001", "High": "33.140999", "Low": "30.74", "Date": "2015-12-31", "Adj_Close": "32.330002", "Close": "32.330002", "Symbol": "GBT"}, {"Volume": "146200", "Open": "32.41", "High": "32.650002", "Low": "31.33", "Date": "2015-12-30", "Adj_Close": "31.40", "Close": "31.40", "Symbol": "GBT"}, {"Volume": "310500", "Open": "33.049999", "High": "33.599998", "Low": "31.565001", "Date": "2015-12-29", "Adj_Close": "32.619999", "Close": "32.619999", "Symbol": "GBT"}, {"Volume": "98000", "Open": "33.43", "High": "34.209999", "Low": "32.474998", "Date": "2015-12-28", "Adj_Close": "32.900002", "Close": "32.900002", "Symbol": "GBT"}, {"Volume": "79700", "Open": "33.110001", "High": "33.955002", "Low": "33.049999", "Date": "2015-12-24", "Adj_Close": "33.540001", "Close": "33.540001", "Symbol": "GBT"}, {"Volume": "137900", "Open": "31.030001", "High": "32.91", "Low": "30.99", "Date": "2015-12-23", "Adj_Close": "32.779999", "Close": "32.779999", "Symbol": "GBT"}, {"Volume": "254500", "Open": "30.610001", "High": "31.950001", "Low": "30.030001", "Date": "2015-12-22", "Adj_Close": "30.879999", "Close": "30.879999", "Symbol": "GBT"}, {"Volume": "167700", "Open": "30.85", "High": "31.67", "Low": "30.190001", "Date": "2015-12-21", "Adj_Close": "30.42", "Close": "30.42", "Symbol": "GBT"}, {"Volume": "1000300", "Open": "33.59", "High": "34.330002", "Low": "30.379999", "Date": "2015-12-18", "Adj_Close": "30.379999", "Close": "30.379999", "Symbol": "GBT"}, {"Volume": "173200", "Open": "34.189999", "High": "35.369999", "Low": "33.619999", "Date": "2015-12-17", "Adj_Close": "33.66", "Close": "33.66", "Symbol": "GBT"}, {"Volume": "169600", "Open": "33.25", "High": "34.59", "Low": "32.98", "Date": "2015-12-16", "Adj_Close": "34.439999", "Close": "34.439999", "Symbol": "GBT"}, {"Volume": "324700", "Open": "32.330002", "High": "33.240002", "Low": "31.98", "Date": "2015-12-15", "Adj_Close": "33.02", "Close": "33.02", "Symbol": "GBT"}, {"Volume": "536100", "Open": "33.23", "High": "33.57", "Low": "31.690001", "Date": "2015-12-14", "Adj_Close": "31.889999", "Close": "31.889999", "Symbol": "GBT"}, {"Volume": "179000", "Open": "33.740002", "High": "34.540001", "Low": "32.779999", "Date": "2015-12-11", "Adj_Close": "33.110001", "Close": "33.110001", "Symbol": "GBT"}, {"Volume": "308500", "Open": "33.759998", "High": "35.00", "Low": "33.50", "Date": "2015-12-10", "Adj_Close": "34.169998", "Close": "34.169998", "Symbol": "GBT"}, {"Volume": "693200", "Open": "33.549999", "High": "34.740002", "Low": "33.088001", "Date": "2015-12-09", "Adj_Close": "34.360001", "Close": "34.360001", "Symbol": "GBT"}, {"Volume": "1221400", "Open": "33.939999", "High": "36.50", "Low": "28.725", "Date": "2015-12-08", "Adj_Close": "33.369999", "Close": "33.369999", "Symbol": "GBT"}, {"Volume": "3021400", "Open": "38.82", "High": "39.900002", "Low": "33.014999", "Date": "2015-12-07", "Adj_Close": "33.93", "Close": "33.93", "Symbol": "GBT"}, {"Volume": "475500", "Open": "51.18", "High": "51.950001", "Low": "44.34", "Date": "2015-12-04", "Adj_Close": "45.669998", "Close": "45.669998", "Symbol": "GBT"}, {"Volume": "293500", "Open": "50.700001", "High": "51.639999", "Low": "49.709999", "Date": "2015-12-03", "Adj_Close": "51.119999", "Close": "51.119999", "Symbol": "GBT"}, {"Volume": "331700", "Open": "47.040001", "High": "50.50", "Low": "47.040001", "Date": "2015-12-02", "Adj_Close": "50.48", "Close": "50.48", "Symbol": "GBT"}, {"Volume": "524900", "Open": "46.959999", "High": "47.950001", "Low": "44.509998", "Date": "2015-12-01", "Adj_Close": "47.330002", "Close": "47.330002", "Symbol": "GBT"}, {"Volume": "311700", "Open": "49.66", "High": "54.990002", "Low": "46.220001", "Date": "2015-11-30", "Adj_Close": "46.959999", "Close": "46.959999", "Symbol": "GBT"}, {"Volume": "68100", "Open": "49.799999", "High": "50.819", "Low": "48.950001", "Date": "2015-11-27", "Adj_Close": "49.360001", "Close": "49.360001", "Symbol": "GBT"}, {"Volume": "293300", "Open": "48.970001", "High": "50.66", "Low": "48.369999", "Date": "2015-11-25", "Adj_Close": "49.73", "Close": "49.73", "Symbol": "GBT"}, {"Volume": "522900", "Open": "49.540001", "High": "50.575001", "Low": "48.02", "Date": "2015-11-24", "Adj_Close": "48.700001", "Close": "48.700001", "Symbol": "GBT"}, {"Volume": "239100", "Open": "51.439999", "High": "51.596001", "Low": "49.169998", "Date": "2015-11-23", "Adj_Close": "49.599998", "Close": "49.599998", "Symbol": "GBT"}, {"Volume": "360600", "Open": "50.080002", "High": "54.240002", "Low": "49.568001", "Date": "2015-11-20", "Adj_Close": "51.849998", "Close": "51.849998", "Symbol": "GBT"}, {"Volume": "355700", "Open": "54.43", "High": "54.57", "Low": "49.990002", "Date": "2015-11-19", "Adj_Close": "50.09", "Close": "50.09", "Symbol": "GBT"}, {"Volume": "432700", "Open": "47.049999", "High": "55.740002", "Low": "47.049999", "Date": "2015-11-18", "Adj_Close": "54.66", "Close": "54.66", "Symbol": "GBT"}, {"Volume": "184700", "Open": "43.599998", "High": "48.110001", "Low": "42.759998", "Date": "2015-11-17", "Adj_Close": "46.860001", "Close": "46.860001", "Symbol": "GBT"}, {"Volume": "188600", "Open": "45.490002", "High": "45.775002", "Low": "43.02", "Date": "2015-11-16", "Adj_Close": "43.549999", "Close": "43.549999", "Symbol": "GBT"}, {"Volume": "226800", "Open": "41.630001", "High": "45.48", "Low": "41.421001", "Date": "2015-11-13", "Adj_Close": "45.349998", "Close": "45.349998", "Symbol": "GBT"}, {"Volume": "174700", "Open": "43.509998", "High": "43.580002", "Low": "40.599998", "Date": "2015-11-12", "Adj_Close": "41.759998", "Close": "41.759998", "Symbol": "GBT"}, {"Volume": "182700", "Open": "44.200001", "High": "44.610001", "Low": "43.189999", "Date": "2015-11-11", "Adj_Close": "43.66", "Close": "43.66", "Symbol": "GBT"}, {"Volume": "219200", "Open": "44.259998", "High": "44.860001", "Low": "42.209999", "Date": "2015-11-10", "Adj_Close": "43.950001", "Close": "43.950001", "Symbol": "GBT"}, {"Volume": "796400", "Open": "44.75", "High": "44.77", "Low": "42.029999", "Date": "2015-11-09", "Adj_Close": "44.529999", "Close": "44.529999", "Symbol": "GBT"}, {"Volume": "260500", "Open": "47.34", "High": "47.689999", "Low": "44.099998", "Date": "2015-11-06", "Adj_Close": "44.830002", "Close": "44.830002", "Symbol": "GBT"}, {"Volume": "152900", "Open": "50.060001", "High": "50.560001", "Low": "47.759998", "Date": "2015-11-05", "Adj_Close": "47.889999", "Close": "47.889999", "Symbol": "GBT"}, {"Volume": "239400", "Open": "49.75", "High": "50.665001", "Low": "48.02", "Date": "2015-11-04", "Adj_Close": "49.799999", "Close": "49.799999", "Symbol": "GBT"}, {"Volume": "165700", "Open": "47.330002", "High": "51.91", "Low": "47.330002", "Date": "2015-11-03", "Adj_Close": "51.009998", "Close": "51.009998", "Symbol": "GBT"}, {"Volume": "127200", "Open": "47.220001", "High": "48.50", "Low": "46.549999", "Date": "2015-11-02", "Adj_Close": "48.290001", "Close": "48.290001", "Symbol": "GBT"}, {"Volume": "64000", "Open": "45.91", "High": "46.849998", "Low": "45.57", "Date": "2015-10-30", "Adj_Close": "46.630001", "Close": "46.630001", "Symbol": "GBT"}, {"Volume": "47500", "Open": "46.98", "High": "47.360001", "Low": "45.779999", "Date": "2015-10-29", "Adj_Close": "46.049999", "Close": "46.049999", "Symbol": "GBT"}, {"Volume": "191200", "Open": "46.240002", "High": "47.25", "Low": "45.599998", "Date": "2015-10-28", "Adj_Close": "47.07", "Close": "47.07", "Symbol": "GBT"}, {"Volume": "138500", "Open": "46.57", "High": "47.25", "Low": "45.880001", "Date": "2015-10-27", "Adj_Close": "45.98", "Close": "45.98", "Symbol": "GBT"}, {"Volume": "120600", "Open": "45.709999", "High": "47.880001", "Low": "44.139999", "Date": "2015-10-26", "Adj_Close": "46.919998", "Close": "46.919998", "Symbol": "GBT"}, {"Volume": "110200", "Open": "45.68", "High": "47.68", "Low": "45.240002", "Date": "2015-10-23", "Adj_Close": "45.849998", "Close": "45.849998", "Symbol": "GBT"}, {"Volume": "204100", "Open": "45.00", "High": "46.040001", "Low": "44.25", "Date": "2015-10-22", "Adj_Close": "45.060001", "Close": "45.060001", "Symbol": "GBT"}, {"Volume": "191800", "Open": "48.810001", "High": "49.200001", "Low": "44.48", "Date": "2015-10-21", "Adj_Close": "44.689999", "Close": "44.689999", "Symbol": "GBT"}, {"Volume": "140600", "Open": "49.52", "High": "50.125999", "Low": "47.400002", "Date": "2015-10-20", "Adj_Close": "48.419998", "Close": "48.419998", "Symbol": "GBT"}, {"Volume": "203900", "Open": "46.400002", "High": "50.98", "Low": "45.776001", "Date": "2015-10-19", "Adj_Close": "49.209999", "Close": "49.209999", "Symbol": "GBT"}, {"Volume": "75000", "Open": "47.389999", "High": "47.459999", "Low": "45.869999", "Date": "2015-10-16", "Adj_Close": "46.919998", "Close": "46.919998", "Symbol": "GBT"}, {"Volume": "113600", "Open": "47.220001", "High": "47.66", "Low": "45.669998", "Date": "2015-10-15", "Adj_Close": "47.029999", "Close": "47.029999", "Symbol": "GBT"}, {"Volume": "136500", "Open": "46.93", "High": "47.613998", "Low": "45.244999", "Date": "2015-10-14", "Adj_Close": "47.240002", "Close": "47.240002", "Symbol": "GBT"}, {"Volume": "219200", "Open": "47.450001", "High": "48.150002", "Low": "46.50", "Date": "2015-10-13", "Adj_Close": "47.00", "Close": "47.00", "Symbol": "GBT"}, {"Volume": "120900", "Open": "48.509998", "High": "49.264", "Low": "47.57", "Date": "2015-10-12", "Adj_Close": "47.700001", "Close": "47.700001", "Symbol": "GBT"}, {"Volume": "30400", "Open": "48.00", "High": "49.080002", "Low": "47.919998", "Date": "2015-10-09", "Adj_Close": "48.389999", "Close": "48.389999", "Symbol": "GBT"}, {"Volume": "103100", "Open": "48.669998", "High": "48.900002", "Low": "47.049999", "Date": "2015-10-08", "Adj_Close": "48.080002", "Close": "48.080002", "Symbol": "GBT"}, {"Volume": "168000", "Open": "48.310001", "High": "49.535", "Low": "46.77", "Date": "2015-10-07", "Adj_Close": "49.110001", "Close": "49.110001", "Symbol": "GBT"}, {"Volume": "164500", "Open": "48.91", "High": "49.389999", "Low": "46.259998", "Date": "2015-10-06", "Adj_Close": "48.040001", "Close": "48.040001", "Symbol": "GBT"}, {"Volume": "133900", "Open": "47.50", "High": "51.240002", "Low": "47.130001", "Date": "2015-10-05", "Adj_Close": "49.23", "Close": "49.23", "Symbol": "GBT"}, {"Volume": "132600", "Open": "42.889999", "High": "46.98", "Low": "42.814999", "Date": "2015-10-02", "Adj_Close": "46.889999", "Close": "46.889999", "Symbol": "GBT"}, {"Volume": "223600", "Open": "42.50", "High": "44.43", "Low": "40.924999", "Date": "2015-10-01", "Adj_Close": "43.700001", "Close": "43.700001", "Symbol": "GBT"}, {"Volume": "1146300", "Open": "40.290001", "High": "45.07", "Low": "40.290001", "Date": "2015-09-30", "Adj_Close": "42.16", "Close": "42.16", "Symbol": "GBT"}, {"Volume": "295400", "Open": "38.060001", "High": "43.740002", "Low": "36.474998", "Date": "2015-09-29", "Adj_Close": "39.91", "Close": "39.91", "Symbol": "GBT"}, {"Volume": "369700", "Open": "44.860001", "High": "45.59", "Low": "36.360001", "Date": "2015-09-28", "Adj_Close": "37.740002", "Close": "37.740002", "Symbol": "GBT"}, {"Volume": "130400", "Open": "46.555", "High": "47.57", "Low": "43.790001", "Date": "2015-09-25", "Adj_Close": "44.84", "Close": "44.84", "Symbol": "GBT"}, {"Volume": "100200", "Open": "46.169998", "High": "46.689999", "Low": "44.900002", "Date": "2015-09-24", "Adj_Close": "45.580002", "Close": "45.580002", "Symbol": "GBT"}, {"Volume": "73900", "Open": "46.34", "High": "47.689999", "Low": "46.07", "Date": "2015-09-23", "Adj_Close": "46.490002", "Close": "46.490002", "Symbol": "GBT"}, {"Volume": "264500", "Open": "47.07", "High": "48.845001", "Low": "43.290001", "Date": "2015-09-22", "Adj_Close": "45.970001", "Close": "45.970001", "Symbol": "GBT"}, {"Volume": "180000", "Open": "53.950001", "High": "53.950001", "Low": "47.02", "Date": "2015-09-21", "Adj_Close": "47.25", "Close": "47.25", "Symbol": "GBT"}, {"Volume": "149700", "Open": "51.220001", "High": "52.68", "Low": "51.220001", "Date": "2015-09-18", "Adj_Close": "52.209999", "Close": "52.209999", "Symbol": "GBT"}, {"Volume": "73900", "Open": "52.009998", "High": "52.709999", "Low": "51.27", "Date": "2015-09-17", "Adj_Close": "52.165001", "Close": "52.165001", "Symbol": "GBT"}, {"Volume": "84200", "Open": "52.889999", "High": "53.490002", "Low": "52.02", "Date": "2015-09-16", "Adj_Close": "52.259998", "Close": "52.259998", "Symbol": "GBT"}, {"Volume": "46600", "Open": "52.630001", "High": "54.00", "Low": "52.610001", "Date": "2015-09-15", "Adj_Close": "53.400002", "Close": "53.400002", "Symbol": "GBT"}, {"Volume": "37800", "Open": "53.060001", "High": "53.645", "Low": "51.02", "Date": "2015-09-14", "Adj_Close": "52.75", "Close": "52.75", "Symbol": "GBT"}, {"Volume": "54000", "Open": "53.060001", "High": "53.355", "Low": "51.799999", "Date": "2015-09-11", "Adj_Close": "52.720001", "Close": "52.720001", "Symbol": "GBT"}, {"Volume": "57400", "Open": "52.490002", "High": "53.964001", "Low": "51.790001", "Date": "2015-09-10", "Adj_Close": "53.07", "Close": "53.07", "Symbol": "GBT"}, {"Volume": "73400", "Open": "52.57", "High": "53.00", "Low": "51.330002", "Date": "2015-09-09", "Adj_Close": "52.740002", "Close": "52.740002", "Symbol": "GBT"}, {"Volume": "293800", "Open": "54.00", "High": "57.00", "Low": "49.630001", "Date": "2015-09-08", "Adj_Close": "52.290001", "Close": "52.290001", "Symbol": "GBT"}, {"Volume": "49400", "Open": "51.700001", "High": "52.965", "Low": "50.709999", "Date": "2015-09-04", "Adj_Close": "52.700001", "Close": "52.700001", "Symbol": "GBT"}, {"Volume": "162100", "Open": "51.75", "High": "52.895", "Low": "51.009998", "Date": "2015-09-03", "Adj_Close": "52.349998", "Close": "52.349998", "Symbol": "GBT"}, {"Volume": "246200", "Open": "49.049999", "High": "52.00", "Low": "48.689999", "Date": "2015-09-02", "Adj_Close": "52.00", "Close": "52.00", "Symbol": "GBT"}, {"Volume": "76900", "Open": "47.509998", "High": "50.00", "Low": "46.509998", "Date": "2015-09-01", "Adj_Close": "49.150002", "Close": "49.150002", "Symbol": "GBT"}, {"Volume": "275000", "Open": "45.68", "High": "50.50", "Low": "45.445", "Date": "2015-08-31", "Adj_Close": "49.490002", "Close": "49.490002", "Symbol": "GBT"}, {"Volume": "114500", "Open": "41.779999", "High": "46.950001", "Low": "40.66", "Date": "2015-08-28", "Adj_Close": "45.439999", "Close": "45.439999", "Symbol": "GBT"}, {"Volume": "77200", "Open": "41.68", "High": "42.700001", "Low": "41.513", "Date": "2015-08-27", "Adj_Close": "42.200001", "Close": "42.200001", "Symbol": "GBT"}, {"Volume": "301500", "Open": "44.32", "High": "44.32", "Low": "38.509998", "Date": "2015-08-26", "Adj_Close": "40.759998", "Close": "40.759998", "Symbol": "GBT"}, {"Volume": "108700", "Open": "45.50", "High": "45.50", "Low": "40.00", "Date": "2015-08-25", "Adj_Close": "42.869999", "Close": "42.869999", "Symbol": "GBT"}, {"Volume": "310200", "Open": "42.810001", "High": "42.810001", "Low": "36.362999", "Date": "2015-08-24", "Adj_Close": "39.509998", "Close": "39.509998", "Symbol": "GBT"}, {"Volume": "422600", "Open": "44.099998", "High": "46.028", "Low": "42.23", "Date": "2015-08-21", "Adj_Close": "45.599998", "Close": "45.599998", "Symbol": "GBT"}, {"Volume": "247300", "Open": "43.560001", "High": "46.369999", "Low": "42.07", "Date": "2015-08-20", "Adj_Close": "44.990002", "Close": "44.990002", "Symbol": "GBT"}, {"Volume": "263600", "Open": "45.549999", "High": "45.950001", "Low": "41.240002", "Date": "2015-08-19", "Adj_Close": "44.16", "Close": "44.16", "Symbol": "GBT"}, {"Volume": "694500", "Open": "52.950001", "High": "52.950001", "Low": "44.650002", "Date": "2015-08-18", "Adj_Close": "45.060001", "Close": "45.060001", "Symbol": "GBT"}, {"Volume": "808400", "Open": "46.25", "High": "55.439999", "Low": "45.810001", "Date": "2015-08-17", "Adj_Close": "53.490002", "Close": "53.490002", "Symbol": "GBT"}, {"Volume": "379300", "Open": "39.450001", "High": "46.889999", "Low": "38.990002", "Date": "2015-08-14", "Adj_Close": "45.669998", "Close": "45.669998", "Symbol": "GBT"}, {"Volume": "822200", "Open": "41.02", "High": "42.00", "Low": "37.160999", "Date": "2015-08-13", "Adj_Close": "39.029999", "Close": "39.029999", "Symbol": "GBT"}, {"Volume": "6957400", "Open": "34.650002", "High": "47.380001", "Low": "33.009998", "Date": "2015-08-12", "Adj_Close": "43.110001", "Close": "43.110001", "Symbol": "GBT"}]