[{"High": "27.59", "Open": "27.360001", "Close": "27.440001", "Low": "27.347", "Date": "2017-03-03", "Volume": "2200", "Adj_Close": "27.440001", "Symbol": "WTFCM"}, {"High": "27.879999", "Open": "27.594999", "Close": "27.531", "Low": "27.52", "Date": "2017-03-02", "Volume": "3200", "Adj_Close": "27.531", "Symbol": "WTFCM"}, {"High": "27.874001", "Open": "27.66", "Close": "27.740999", "Low": "27.610001", "Date": "2017-03-01", "Volume": "1200", "Adj_Close": "27.740999", "Symbol": "WTFCM"}, {"High": "28.00", "Open": "27.521", "Close": "27.74", "Low": "27.521", "Date": "2017-02-28", "Volume": "2200", "Adj_Close": "27.74", "Symbol": "WTFCM"}, {"High": "27.90", "Open": "27.82", "Close": "27.52", "Low": "27.43", "Date": "2017-02-27", "Volume": "3500", "Adj_Close": "27.52", "Symbol": "WTFCM"}, {"High": "27.788", "Open": "27.51", "Close": "27.73", "Low": "27.349001", "Date": "2017-02-24", "Volume": "2100", "Adj_Close": "27.73", "Symbol": "WTFCM"}, {"High": "27.709999", "Open": "27.48", "Close": "27.709999", "Low": "27.43", "Date": "2017-02-23", "Volume": "4800", "Adj_Close": "27.709999", "Symbol": "WTFCM"}, {"High": "27.549999", "Open": "27.25", "Close": "27.389999", "Low": "27.25", "Date": "2017-02-22", "Volume": "4200", "Adj_Close": "27.389999", "Symbol": "WTFCM"}, {"High": "27.50", "Open": "27.35", "Close": "27.50", "Low": "26.990999", "Date": "2017-02-21", "Volume": "5700", "Adj_Close": "27.50", "Symbol": "WTFCM"}, {"High": "27.820999", "Open": "27.620001", "Close": "27.299999", "Low": "26.950001", "Date": "2017-02-17", "Volume": "9600", "Adj_Close": "27.299999", "Symbol": "WTFCM"}, {"High": "27.950001", "Open": "27.870001", "Close": "27.790001", "Low": "27.559999", "Date": "2017-02-16", "Volume": "4100", "Adj_Close": "27.790001", "Symbol": "WTFCM"}, {"High": "27.99", "Open": "27.551001", "Close": "27.959999", "Low": "27.504999", "Date": "2017-02-15", "Volume": "3700", "Adj_Close": "27.959999", "Symbol": "WTFCM"}, {"High": "27.93", "Open": "27.639999", "Close": "27.67", "Low": "27.43", "Date": "2017-02-14", "Volume": "5800", "Adj_Close": "27.67", "Symbol": "WTFCM"}, {"High": "28.00", "Open": "27.74", "Close": "27.85", "Low": "27.73", "Date": "2017-02-13", "Volume": "7700", "Adj_Close": "27.85", "Symbol": "WTFCM"}, {"High": "27.955", "Open": "27.620001", "Close": "27.93", "Low": "27.598", "Date": "2017-02-10", "Volume": "3100", "Adj_Close": "27.93", "Symbol": "WTFCM"}, {"High": "27.98", "Open": "27.209999", "Close": "27.700001", "Low": "27.209999", "Date": "2017-02-09", "Volume": "7700", "Adj_Close": "27.700001", "Symbol": "WTFCM"}, {"High": "27.700001", "Open": "27.52", "Close": "27.561001", "Low": "27.469999", "Date": "2017-02-08", "Volume": "7200", "Adj_Close": "27.561001", "Symbol": "WTFCM"}, {"High": "27.60", "Open": "27.105", "Close": "27.41", "Low": "27.09", "Date": "2017-02-07", "Volume": "8000", "Adj_Close": "27.41", "Symbol": "WTFCM"}, {"High": "27.639999", "Open": "26.961", "Close": "27.50", "Low": "26.961", "Date": "2017-02-06", "Volume": "4600", "Adj_Close": "27.50", "Symbol": "WTFCM"}, {"High": "27.49", "Open": "26.90", "Close": "27.370001", "Low": "26.870001", "Date": "2017-02-03", "Volume": "11700", "Adj_Close": "27.370001", "Symbol": "WTFCM"}, {"High": "27.110001", "Open": "26.85", "Close": "26.959999", "Low": "26.85", "Date": "2017-02-02", "Volume": "3000", "Adj_Close": "26.959999", "Symbol": "WTFCM"}, {"High": "27.091999", "Open": "26.85", "Close": "26.889999", "Low": "26.809999", "Date": "2017-02-01", "Volume": "7400", "Adj_Close": "26.889999", "Symbol": "WTFCM"}, {"High": "27.07", "Open": "26.950001", "Close": "26.950001", "Low": "26.84", "Date": "2017-01-31", "Volume": "4100", "Adj_Close": "26.950001", "Symbol": "WTFCM"}, {"High": "27.15", "Open": "26.91", "Close": "27.139999", "Low": "26.91", "Date": "2017-01-30", "Volume": "5700", "Adj_Close": "27.139999", "Symbol": "WTFCM"}, {"High": "27.111", "Open": "26.604", "Close": "27.02", "Low": "26.51", "Date": "2017-01-27", "Volume": "6000", "Adj_Close": "27.02", "Symbol": "WTFCM"}, {"High": "27.104", "Open": "26.809999", "Close": "26.936001", "Low": "26.50", "Date": "2017-01-26", "Volume": "4900", "Adj_Close": "26.936001", "Symbol": "WTFCM"}, {"High": "27.135", "Open": "26.93", "Close": "27.049999", "Low": "26.92", "Date": "2017-01-25", "Volume": "4200", "Adj_Close": "27.049999", "Symbol": "WTFCM"}, {"High": "27.15", "Open": "27.02", "Close": "27.08", "Low": "27.02", "Date": "2017-01-24", "Volume": "2700", "Adj_Close": "27.08", "Symbol": "WTFCM"}, {"High": "27.190001", "Open": "26.92", "Close": "27.02", "Low": "26.919001", "Date": "2017-01-23", "Volume": "8300", "Adj_Close": "27.02", "Symbol": "WTFCM"}, {"High": "27.190001", "Open": "26.549999", "Close": "27.190001", "Low": "26.549999", "Date": "2017-01-20", "Volume": "6500", "Adj_Close": "27.190001", "Symbol": "WTFCM"}, {"High": "27.200001", "Open": "26.799999", "Close": "26.780001", "Low": "26.35", "Date": "2017-01-19", "Volume": "16900", "Adj_Close": "26.780001", "Symbol": "WTFCM"}, {"High": "27.200001", "Open": "27.139999", "Close": "27.049999", "Low": "26.657", "Date": "2017-01-18", "Volume": "2900", "Adj_Close": "27.049999", "Symbol": "WTFCM"}, {"High": "27.221001", "Open": "27.08", "Close": "27.200001", "Low": "26.620001", "Date": "2017-01-17", "Volume": "9600", "Adj_Close": "27.200001", "Symbol": "WTFCM"}, {"High": "27.42", "Open": "27.200001", "Close": "27.17", "Low": "26.749001", "Date": "2017-01-13", "Volume": "4000", "Adj_Close": "27.17", "Symbol": "WTFCM"}, {"High": "27.059999", "Open": "26.879999", "Close": "26.85", "Low": "26.60", "Date": "2017-01-12", "Volume": "8500", "Adj_Close": "26.85", "Symbol": "WTFCM"}, {"High": "26.84", "Open": "26.540001", "Close": "26.82", "Low": "26.190001", "Date": "2017-01-11", "Volume": "11600", "Adj_Close": "26.82", "Symbol": "WTFCM"}, {"High": "26.74", "Open": "26.68", "Close": "26.639999", "Low": "26.483999", "Date": "2017-01-10", "Volume": "6300", "Adj_Close": "26.639999", "Symbol": "WTFCM"}, {"High": "26.709999", "Open": "26.709999", "Close": "26.58", "Low": "26.25", "Date": "2017-01-09", "Volume": "12100", "Adj_Close": "26.58", "Symbol": "WTFCM"}, {"High": "26.639999", "Open": "26.27", "Close": "26.59", "Low": "26.00", "Date": "2017-01-06", "Volume": "8000", "Adj_Close": "26.59", "Symbol": "WTFCM"}, {"High": "26.67", "Open": "26.67", "Close": "26.40", "Low": "26.049999", "Date": "2017-01-05", "Volume": "10000", "Adj_Close": "26.40", "Symbol": "WTFCM"}, {"High": "26.559999", "Open": "26.24", "Close": "26.530001", "Low": "26.24", "Date": "2017-01-04", "Volume": "8300", "Adj_Close": "26.530001", "Symbol": "WTFCM"}, {"High": "26.205999", "Open": "25.879999", "Close": "26.190001", "Low": "25.879999", "Date": "2017-01-03", "Volume": "7600", "Adj_Close": "26.190001", "Symbol": "WTFCM"}, {"High": "26.059", "Open": "25.92", "Close": "25.870001", "Low": "25.870001", "Date": "2016-12-30", "Volume": "4200", "Adj_Close": "25.870001", "Symbol": "WTFCM"}, {"High": "26.083", "Open": "25.860001", "Close": "26.02", "Low": "25.860001", "Date": "2016-12-29", "Volume": "5700", "Adj_Close": "26.02", "Symbol": "WTFCM"}, {"High": "26.110001", "Open": "26.110001", "Close": "25.969999", "Low": "25.889999", "Date": "2016-12-28", "Volume": "7600", "Adj_Close": "25.969999", "Symbol": "WTFCM"}, {"High": "26.35", "Open": "26.24", "Close": "26.309999", "Low": "26.10", "Date": "2016-12-27", "Volume": "7200", "Adj_Close": "25.899999", "Symbol": "WTFCM"}, {"High": "26.41", "Open": "26.219999", "Close": "26.34", "Low": "26.110001", "Date": "2016-12-23", "Volume": "8500", "Adj_Close": "25.929532", "Symbol": "WTFCM"}, {"High": "26.348", "Open": "26.15", "Close": "26.16", "Low": "25.851", "Date": "2016-12-22", "Volume": "9300", "Adj_Close": "25.752337", "Symbol": "WTFCM"}, {"High": "26.360001", "Open": "25.950001", "Close": "26.33", "Low": "25.809999", "Date": "2016-12-21", "Volume": "5200", "Adj_Close": "25.919688", "Symbol": "WTFCM"}, {"High": "26.280001", "Open": "26.030001", "Close": "26.110001", "Low": "25.940001", "Date": "2016-12-20", "Volume": "6000", "Adj_Close": "25.703117", "Symbol": "WTFCM"}, {"High": "26.66", "Open": "26.040001", "Close": "26.120001", "Low": "26.040001", "Date": "2016-12-19", "Volume": "10800", "Adj_Close": "25.712961", "Symbol": "WTFCM"}, {"High": "26.382", "Open": "25.82", "Close": "25.950001", "Low": "25.82", "Date": "2016-12-16", "Volume": "4100", "Adj_Close": "25.54561", "Symbol": "WTFCM"}, {"High": "26.325001", "Open": "25.780001", "Close": "25.870001", "Low": "25.76", "Date": "2016-12-15", "Volume": "12400", "Adj_Close": "25.466857", "Symbol": "WTFCM"}, {"High": "25.98", "Open": "25.65", "Close": "25.98", "Low": "25.65", "Date": "2016-12-14", "Volume": "12900", "Adj_Close": "25.575141", "Symbol": "WTFCM"}, {"High": "26.374001", "Open": "26.00", "Close": "25.690001", "Low": "25.620001", "Date": "2016-12-13", "Volume": "62000", "Adj_Close": "25.289662", "Symbol": "WTFCM"}, {"High": "26.444", "Open": "25.77", "Close": "25.879999", "Low": "25.77", "Date": "2016-12-12", "Volume": "12400", "Adj_Close": "25.476699", "Symbol": "WTFCM"}, {"High": "26.15", "Open": "25.700001", "Close": "25.85", "Low": "25.610001", "Date": "2016-12-09", "Volume": "12300", "Adj_Close": "25.447168", "Symbol": "WTFCM"}, {"High": "26.777", "Open": "25.860001", "Close": "25.681999", "Low": "25.65", "Date": "2016-12-08", "Volume": "18100", "Adj_Close": "25.281785", "Symbol": "WTFCM"}, {"High": "26.802999", "Open": "26.190001", "Close": "25.99", "Low": "25.561001", "Date": "2016-12-07", "Volume": "49100", "Adj_Close": "25.584986", "Symbol": "WTFCM"}, {"High": "26.778999", "Open": "26.469999", "Close": "26.120001", "Low": "26.049999", "Date": "2016-12-06", "Volume": "11000", "Adj_Close": "25.712961", "Symbol": "WTFCM"}, {"High": "27.120001", "Open": "26.860001", "Close": "26.450001", "Low": "26.450001", "Date": "2016-12-05", "Volume": "35500", "Adj_Close": "26.037818", "Symbol": "WTFCM"}, {"High": "28.40", "Open": "26.60", "Close": "26.85", "Low": "26.60", "Date": "2016-12-02", "Volume": "11100", "Adj_Close": "26.431585", "Symbol": "WTFCM"}, {"High": "26.92", "Open": "26.92", "Close": "26.51", "Low": "26.379999", "Date": "2016-12-01", "Volume": "5900", "Adj_Close": "26.096883", "Symbol": "WTFCM"}, {"High": "27.82", "Open": "27.809999", "Close": "27.129999", "Low": "27.02", "Date": "2016-11-30", "Volume": "11700", "Adj_Close": "26.70722", "Symbol": "WTFCM"}, {"High": "27.65", "Open": "26.950001", "Close": "27.08", "Low": "26.950001", "Date": "2016-11-29", "Volume": "11000", "Adj_Close": "26.658", "Symbol": "WTFCM"}, {"High": "26.99", "Open": "26.68", "Close": "26.98", "Low": "26.68", "Date": "2016-11-28", "Volume": "5900", "Adj_Close": "26.559558", "Symbol": "WTFCM"}, {"High": "26.98", "Open": "26.73", "Close": "26.764", "Low": "26.73", "Date": "2016-11-25", "Volume": "2800", "Adj_Close": "26.346924", "Symbol": "WTFCM"}, {"High": "26.871", "Open": "26.860001", "Close": "26.870001", "Low": "26.74", "Date": "2016-11-23", "Volume": "9200", "Adj_Close": "26.451273", "Symbol": "WTFCM"}, {"High": "26.99", "Open": "26.816", "Close": "26.959999", "Low": "26.735001", "Date": "2016-11-22", "Volume": "4800", "Adj_Close": "26.539869", "Symbol": "WTFCM"}, {"High": "26.969999", "Open": "26.870001", "Close": "26.870001", "Low": "26.50", "Date": "2016-11-21", "Volume": "8500", "Adj_Close": "26.451273", "Symbol": "WTFCM"}, {"High": "26.948", "Open": "26.40", "Close": "26.50", "Low": "26.24", "Date": "2016-11-18", "Volume": "7300", "Adj_Close": "26.087038", "Symbol": "WTFCM"}, {"High": "26.549999", "Open": "26.540001", "Close": "26.450001", "Low": "26.10", "Date": "2016-11-17", "Volume": "18500", "Adj_Close": "26.037818", "Symbol": "WTFCM"}, {"High": "26.799999", "Open": "26.52", "Close": "26.799999", "Low": "26.235001", "Date": "2016-11-16", "Volume": "30000", "Adj_Close": "26.382363", "Symbol": "WTFCM"}, {"High": "26.950001", "Open": "25.780001", "Close": "26.379999", "Low": "25.75", "Date": "2016-11-15", "Volume": "14000", "Adj_Close": "25.968908", "Symbol": "WTFCM"}, {"High": "26.01", "Open": "25.940001", "Close": "25.76", "Low": "25.43", "Date": "2016-11-14", "Volume": "26400", "Adj_Close": "25.35857", "Symbol": "WTFCM"}, {"High": "26.538", "Open": "26.538", "Close": "26.17", "Low": "25.49", "Date": "2016-11-11", "Volume": "30300", "Adj_Close": "25.762181", "Symbol": "WTFCM"}, {"High": "26.66", "Open": "26.41", "Close": "26.469999", "Low": "26.254999", "Date": "2016-11-10", "Volume": "22100", "Adj_Close": "26.057505", "Symbol": "WTFCM"}, {"High": "27.247", "Open": "26.672001", "Close": "26.860001", "Low": "26.448999", "Date": "2016-11-09", "Volume": "6200", "Adj_Close": "26.441429", "Symbol": "WTFCM"}, {"High": "27.389999", "Open": "26.90", "Close": "27.389999", "Low": "26.90", "Date": "2016-11-08", "Volume": "13900", "Adj_Close": "26.963169", "Symbol": "WTFCM"}, {"High": "26.950001", "Open": "26.91", "Close": "26.950001", "Low": "26.761999", "Date": "2016-11-07", "Volume": "4500", "Adj_Close": "26.530027", "Symbol": "WTFCM"}, {"High": "27.389999", "Open": "26.530001", "Close": "27.389999", "Low": "26.49", "Date": "2016-11-04", "Volume": "10300", "Adj_Close": "26.963169", "Symbol": "WTFCM"}, {"High": "27.497999", "Open": "27.42", "Close": "26.785", "Low": "26.459999", "Date": "2016-11-03", "Volume": "5000", "Adj_Close": "26.367597", "Symbol": "WTFCM"}, {"High": "28.041", "Open": "27.60", "Close": "27.683001", "Low": "27.440001", "Date": "2016-11-02", "Volume": "9800", "Adj_Close": "27.251604", "Symbol": "WTFCM"}, {"High": "28.042", "Open": "27.712999", "Close": "27.77", "Low": "27.655001", "Date": "2016-11-01", "Volume": "6400", "Adj_Close": "27.337248", "Symbol": "WTFCM"}, {"High": "28.115999", "Open": "27.745001", "Close": "27.698999", "Low": "27.698999", "Date": "2016-10-31", "Volume": "4800", "Adj_Close": "27.267353", "Symbol": "WTFCM"}, {"High": "28.110001", "Open": "27.860001", "Close": "27.655001", "Low": "27.634001", "Date": "2016-10-28", "Volume": "6600", "Adj_Close": "27.22404", "Symbol": "WTFCM"}, {"High": "28.589001", "Open": "28.589001", "Close": "27.629999", "Low": "27.629999", "Date": "2016-10-27", "Volume": "11100", "Adj_Close": "27.199428", "Symbol": "WTFCM"}, {"High": "28.280001", "Open": "27.76", "Close": "28.27", "Low": "27.76", "Date": "2016-10-26", "Volume": "5700", "Adj_Close": "27.829456", "Symbol": "WTFCM"}, {"High": "28.558001", "Open": "27.76", "Close": "27.870001", "Low": "27.76", "Date": "2016-10-25", "Volume": "4200", "Adj_Close": "27.43569", "Symbol": "WTFCM"}, {"High": "28.16", "Open": "27.889999", "Close": "27.75", "Low": "27.75", "Date": "2016-10-24", "Volume": "11300", "Adj_Close": "27.317559", "Symbol": "WTFCM"}, {"High": "28.799999", "Open": "27.90", "Close": "27.90", "Low": "27.90", "Date": "2016-10-21", "Volume": "23300", "Adj_Close": "27.465221", "Symbol": "WTFCM"}, {"High": "28.287001", "Open": "27.861", "Close": "28.049999", "Low": "27.548", "Date": "2016-10-20", "Volume": "4900", "Adj_Close": "27.612883", "Symbol": "WTFCM"}, {"High": "28.32", "Open": "27.91", "Close": "28.215", "Low": "27.91", "Date": "2016-10-19", "Volume": "7200", "Adj_Close": "27.775313", "Symbol": "WTFCM"}, {"High": "28.34", "Open": "28.18", "Close": "28.040001", "Low": "27.611", "Date": "2016-10-18", "Volume": "14600", "Adj_Close": "27.603041", "Symbol": "WTFCM"}, {"High": "28.540001", "Open": "28.129999", "Close": "28.134001", "Low": "28.129999", "Date": "2016-10-17", "Volume": "9600", "Adj_Close": "27.695576", "Symbol": "WTFCM"}, {"High": "28.559999", "Open": "28.378", "Close": "28.40", "Low": "28.030001", "Date": "2016-10-14", "Volume": "16400", "Adj_Close": "27.957429", "Symbol": "WTFCM"}, {"High": "28.60", "Open": "28.139999", "Close": "28.562", "Low": "27.440001", "Date": "2016-10-13", "Volume": "9100", "Adj_Close": "28.116906", "Symbol": "WTFCM"}, {"High": "28.669001", "Open": "28.669001", "Close": "28.299999", "Low": "28.098", "Date": "2016-10-12", "Volume": "7000", "Adj_Close": "27.858987", "Symbol": "WTFCM"}, {"High": "28.65", "Open": "28.648001", "Close": "28.59", "Low": "28.59", "Date": "2016-10-11", "Volume": "3000", "Adj_Close": "28.144469", "Symbol": "WTFCM"}, {"High": "29.219999", "Open": "29.219999", "Close": "28.750999", "Low": "28.709999", "Date": "2016-10-10", "Volume": "10600", "Adj_Close": "28.30296", "Symbol": "WTFCM"}, {"High": "29.65", "Open": "28.76", "Close": "29.42", "Low": "28.76", "Date": "2016-10-07", "Volume": "7100", "Adj_Close": "28.961535", "Symbol": "WTFCM"}, {"High": "28.950001", "Open": "28.700001", "Close": "28.950001", "Low": "28.700001", "Date": "2016-10-06", "Volume": "7900", "Adj_Close": "28.49886", "Symbol": "WTFCM"}, {"High": "29.318001", "Open": "29.00", "Close": "28.85", "Low": "28.690001", "Date": "2016-10-05", "Volume": "18100", "Adj_Close": "28.400418", "Symbol": "WTFCM"}, {"High": "29.33", "Open": "28.67", "Close": "28.860001", "Low": "28.67", "Date": "2016-10-04", "Volume": "16600", "Adj_Close": "28.410262", "Symbol": "WTFCM"}, {"High": "29.700001", "Open": "29.700001", "Close": "29.440001", "Low": "28.839001", "Date": "2016-10-03", "Volume": "6500", "Adj_Close": "28.981224", "Symbol": "WTFCM"}, {"High": "29.73", "Open": "29.030001", "Close": "29.43", "Low": "29.030001", "Date": "2016-09-30", "Volume": "7700", "Adj_Close": "28.971379", "Symbol": "WTFCM"}, {"High": "29.540001", "Open": "28.677", "Close": "29.24", "Low": "28.65", "Date": "2016-09-29", "Volume": "3400", "Adj_Close": "28.78434", "Symbol": "WTFCM"}, {"High": "29.959999", "Open": "29.549999", "Close": "29.59", "Low": "28.50", "Date": "2016-09-28", "Volume": "13100", "Adj_Close": "29.128886", "Symbol": "WTFCM"}, {"High": "29.90", "Open": "29.514", "Close": "29.719999", "Low": "29.514", "Date": "2016-09-27", "Volume": "7600", "Adj_Close": "28.853248", "Symbol": "WTFCM"}, {"High": "29.790001", "Open": "29.530001", "Close": "29.740999", "Low": "29.42", "Date": "2016-09-26", "Volume": "6300", "Adj_Close": "28.873636", "Symbol": "WTFCM"}, {"High": "30.00", "Open": "29.334", "Close": "29.50", "Low": "29.334", "Date": "2016-09-23", "Volume": "11400", "Adj_Close": "28.639665", "Symbol": "WTFCM"}, {"High": "29.700001", "Open": "29.68", "Close": "29.50", "Low": "29.40", "Date": "2016-09-22", "Volume": "5100", "Adj_Close": "28.639665", "Symbol": "WTFCM"}, {"High": "29.68", "Open": "29.457001", "Close": "29.572001", "Low": "29.40", "Date": "2016-09-21", "Volume": "10300", "Adj_Close": "28.709566", "Symbol": "WTFCM"}, {"High": "29.99", "Open": "29.459999", "Close": "29.639999", "Low": "29.316999", "Date": "2016-09-20", "Volume": "5100", "Adj_Close": "28.775581", "Symbol": "WTFCM"}, {"High": "29.700001", "Open": "29.540001", "Close": "29.690001", "Low": "29.219999", "Date": "2016-09-19", "Volume": "10100", "Adj_Close": "28.824124", "Symbol": "WTFCM"}, {"High": "29.90", "Open": "29.40", "Close": "29.43", "Low": "29.319", "Date": "2016-09-16", "Volume": "7200", "Adj_Close": "28.571707", "Symbol": "WTFCM"}, {"High": "30.00", "Open": "29.27", "Close": "29.41", "Low": "29.209999", "Date": "2016-09-15", "Volume": "14000", "Adj_Close": "28.55229", "Symbol": "WTFCM"}, {"High": "29.860001", "Open": "29.50", "Close": "29.51", "Low": "29.040001", "Date": "2016-09-14", "Volume": "13800", "Adj_Close": "28.649374", "Symbol": "WTFCM"}, {"High": "30.00", "Open": "29.379999", "Close": "29.370001", "Low": "29.049999", "Date": "2016-09-13", "Volume": "11600", "Adj_Close": "28.513457", "Symbol": "WTFCM"}, {"High": "29.75", "Open": "29.33", "Close": "29.059999", "Low": "29.00", "Date": "2016-09-12", "Volume": "8900", "Adj_Close": "28.212497", "Symbol": "WTFCM"}, {"High": "29.75", "Open": "29.74", "Close": "29.50", "Low": "29.00", "Date": "2016-09-09", "Volume": "5200", "Adj_Close": "28.639665", "Symbol": "WTFCM"}, {"High": "29.959999", "Open": "29.802", "Close": "29.74", "Low": "29.43", "Date": "2016-09-08", "Volume": "17300", "Adj_Close": "28.872665", "Symbol": "WTFCM"}, {"High": "30.00", "Open": "29.327999", "Close": "29.84", "Low": "29.263", "Date": "2016-09-07", "Volume": "30600", "Adj_Close": "28.969749", "Symbol": "WTFCM"}, {"High": "30.00", "Open": "29.097", "Close": "29.82", "Low": "29.097", "Date": "2016-09-06", "Volume": "8500", "Adj_Close": "28.950332", "Symbol": "WTFCM"}, {"High": "30.290001", "Open": "30.290001", "Close": "29.98", "Low": "28.99", "Date": "2016-09-02", "Volume": "16000", "Adj_Close": "29.105666", "Symbol": "WTFCM"}, {"High": "29.995001", "Open": "29.509001", "Close": "29.74", "Low": "29.50", "Date": "2016-09-01", "Volume": "8100", "Adj_Close": "28.872665", "Symbol": "WTFCM"}, {"High": "30.605", "Open": "29.27", "Close": "29.50", "Low": "28.85", "Date": "2016-08-31", "Volume": "17800", "Adj_Close": "28.639665", "Symbol": "WTFCM"}, {"High": "29.50", "Open": "29.351", "Close": "29.030001", "Low": "29.030001", "Date": "2016-08-30", "Volume": "6800", "Adj_Close": "28.183373", "Symbol": "WTFCM"}, {"High": "29.50", "Open": "29.25", "Close": "29.318001", "Low": "28.813999", "Date": "2016-08-29", "Volume": "21500", "Adj_Close": "28.462974", "Symbol": "WTFCM"}, {"High": "29.549999", "Open": "29.549999", "Close": "29.32", "Low": "28.750999", "Date": "2016-08-26", "Volume": "10600", "Adj_Close": "28.464914", "Symbol": "WTFCM"}, {"High": "29.513", "Open": "29.416", "Close": "29.349001", "Low": "28.973", "Date": "2016-08-25", "Volume": "10100", "Adj_Close": "28.49307", "Symbol": "WTFCM"}, {"High": "29.549999", "Open": "29.459999", "Close": "29.540001", "Low": "28.889999", "Date": "2016-08-24", "Volume": "16700", "Adj_Close": "28.678499", "Symbol": "WTFCM"}, {"High": "29.84", "Open": "29.309999", "Close": "29.450001", "Low": "29.309999", "Date": "2016-08-23", "Volume": "16500", "Adj_Close": "28.591124", "Symbol": "WTFCM"}, {"High": "29.93", "Open": "29.775", "Close": "29.66", "Low": "28.989", "Date": "2016-08-22", "Volume": "21700", "Adj_Close": "28.794999", "Symbol": "WTFCM"}, {"High": "29.870001", "Open": "29.780001", "Close": "29.84", "Low": "29.620001", "Date": "2016-08-19", "Volume": "12600", "Adj_Close": "28.969749", "Symbol": "WTFCM"}, {"High": "29.83", "Open": "29.50", "Close": "29.809999", "Low": "29.049999", "Date": "2016-08-18", "Volume": "14300", "Adj_Close": "28.940624", "Symbol": "WTFCM"}, {"High": "29.50", "Open": "29.50", "Close": "29.469999", "Low": "28.77", "Date": "2016-08-17", "Volume": "15800", "Adj_Close": "28.610539", "Symbol": "WTFCM"}, {"High": "29.719999", "Open": "29.365", "Close": "29.559999", "Low": "28.834999", "Date": "2016-08-16", "Volume": "9300", "Adj_Close": "28.697915", "Symbol": "WTFCM"}, {"High": "29.74", "Open": "29.205", "Close": "29.299999", "Low": "29.00", "Date": "2016-08-15", "Volume": "5100", "Adj_Close": "28.445497", "Symbol": "WTFCM"}, {"High": "29.90", "Open": "29.90", "Close": "28.681", "Low": "28.51", "Date": "2016-08-12", "Volume": "7700", "Adj_Close": "27.84455", "Symbol": "WTFCM"}, {"High": "29.950001", "Open": "29.559999", "Close": "29.76", "Low": "28.50", "Date": "2016-08-11", "Volume": "21800", "Adj_Close": "28.892083", "Symbol": "WTFCM"}, {"High": "29.736", "Open": "29.40", "Close": "29.379999", "Low": "29.004", "Date": "2016-08-10", "Volume": "15800", "Adj_Close": "28.523164", "Symbol": "WTFCM"}, {"High": "29.50", "Open": "29.07", "Close": "29.40", "Low": "29.07", "Date": "2016-08-09", "Volume": "13600", "Adj_Close": "28.542581", "Symbol": "WTFCM"}, {"High": "29.450001", "Open": "29.40", "Close": "28.92", "Low": "28.625", "Date": "2016-08-08", "Volume": "16600", "Adj_Close": "28.07658", "Symbol": "WTFCM"}, {"High": "29.48", "Open": "29.25", "Close": "29.200001", "Low": "29.098", "Date": "2016-08-05", "Volume": "23800", "Adj_Close": "28.348415", "Symbol": "WTFCM"}, {"High": "29.370001", "Open": "28.85", "Close": "29.24", "Low": "28.75", "Date": "2016-08-04", "Volume": "19300", "Adj_Close": "28.387247", "Symbol": "WTFCM"}, {"High": "29.33", "Open": "29.33", "Close": "28.82", "Low": "28.542", "Date": "2016-08-03", "Volume": "19500", "Adj_Close": "27.979496", "Symbol": "WTFCM"}, {"High": "29.50", "Open": "29.200001", "Close": "28.98", "Low": "28.98", "Date": "2016-08-02", "Volume": "21600", "Adj_Close": "28.13483", "Symbol": "WTFCM"}, {"High": "29.299999", "Open": "29.129999", "Close": "29.142", "Low": "28.537001", "Date": "2016-08-01", "Volume": "14000", "Adj_Close": "28.292106", "Symbol": "WTFCM"}, {"High": "29.34", "Open": "29.17", "Close": "29.299999", "Low": "28.975", "Date": "2016-07-29", "Volume": "12900", "Adj_Close": "28.445497", "Symbol": "WTFCM"}, {"High": "29.290001", "Open": "29.120001", "Close": "29.18", "Low": "28.648001", "Date": "2016-07-28", "Volume": "16800", "Adj_Close": "28.328998", "Symbol": "WTFCM"}, {"High": "29.15", "Open": "28.85", "Close": "29.063", "Low": "28.559999", "Date": "2016-07-27", "Volume": "16300", "Adj_Close": "28.215409", "Symbol": "WTFCM"}, {"High": "29.15", "Open": "28.74", "Close": "29.120001", "Low": "28.42", "Date": "2016-07-26", "Volume": "13800", "Adj_Close": "28.270748", "Symbol": "WTFCM"}, {"High": "28.702999", "Open": "28.42", "Close": "28.50", "Low": "28.23", "Date": "2016-07-25", "Volume": "13300", "Adj_Close": "27.668829", "Symbol": "WTFCM"}, {"High": "28.889999", "Open": "28.85", "Close": "28.52", "Low": "28.52", "Date": "2016-07-22", "Volume": "14400", "Adj_Close": "27.688246", "Symbol": "WTFCM"}, {"High": "28.912001", "Open": "28.879999", "Close": "28.799999", "Low": "28.52", "Date": "2016-07-21", "Volume": "37700", "Adj_Close": "27.960079", "Symbol": "WTFCM"}, {"High": "28.940001", "Open": "28.549999", "Close": "28.870001", "Low": "28.530001", "Date": "2016-07-20", "Volume": "21200", "Adj_Close": "28.028039", "Symbol": "WTFCM"}, {"High": "29.280001", "Open": "29.280001", "Close": "28.950001", "Low": "28.50", "Date": "2016-07-19", "Volume": "25000", "Adj_Close": "28.105706", "Symbol": "WTFCM"}, {"High": "29.18", "Open": "29.18", "Close": "29.00", "Low": "28.620001", "Date": "2016-07-18", "Volume": "4500", "Adj_Close": "28.154247", "Symbol": "WTFCM"}, {"High": "29.18", "Open": "29.18", "Close": "28.91", "Low": "28.90", "Date": "2016-07-15", "Volume": "30600", "Adj_Close": "28.066872", "Symbol": "WTFCM"}, {"High": "29.08", "Open": "29.08", "Close": "29.02", "Low": "28.190001", "Date": "2016-07-14", "Volume": "16900", "Adj_Close": "28.173664", "Symbol": "WTFCM"}, {"High": "29.25", "Open": "29.25", "Close": "29.08", "Low": "28.90", "Date": "2016-07-13", "Volume": "6800", "Adj_Close": "28.231914", "Symbol": "WTFCM"}, {"High": "29.290001", "Open": "28.98", "Close": "29.26", "Low": "28.52", "Date": "2016-07-12", "Volume": "6300", "Adj_Close": "28.406665", "Symbol": "WTFCM"}, {"High": "28.950001", "Open": "28.950001", "Close": "28.799999", "Low": "28.27", "Date": "2016-07-11", "Volume": "9900", "Adj_Close": "27.960079", "Symbol": "WTFCM"}, {"High": "28.950001", "Open": "28.85", "Close": "28.92", "Low": "28.299999", "Date": "2016-07-08", "Volume": "15500", "Adj_Close": "28.07658", "Symbol": "WTFCM"}, {"High": "28.85", "Open": "28.51", "Close": "28.85", "Low": "28.01", "Date": "2016-07-07", "Volume": "9500", "Adj_Close": "28.008622", "Symbol": "WTFCM"}, {"High": "28.75", "Open": "28.75", "Close": "28.469999", "Low": "28.10", "Date": "2016-07-06", "Volume": "21000", "Adj_Close": "27.639703", "Symbol": "WTFCM"}, {"High": "28.85", "Open": "28.452", "Close": "28.50", "Low": "28.379999", "Date": "2016-07-05", "Volume": "12600", "Adj_Close": "27.668829", "Symbol": "WTFCM"}, {"High": "29.139999", "Open": "28.50", "Close": "28.59", "Low": "28.450001", "Date": "2016-07-01", "Volume": "9700", "Adj_Close": "27.756204", "Symbol": "WTFCM"}, {"High": "28.85", "Open": "28.85", "Close": "28.440001", "Low": "27.790001", "Date": "2016-06-30", "Volume": "19700", "Adj_Close": "27.610579", "Symbol": "WTFCM"}, {"High": "29.02", "Open": "28.799999", "Close": "28.66", "Low": "28.573999", "Date": "2016-06-29", "Volume": "10000", "Adj_Close": "27.824163", "Symbol": "WTFCM"}, {"High": "29.159", "Open": "28.33", "Close": "29.02", "Low": "27.799999", "Date": "2016-06-28", "Volume": "10700", "Adj_Close": "27.775623", "Symbol": "WTFCM"}, {"High": "28.690001", "Open": "28.690001", "Close": "28.24", "Low": "27.860001", "Date": "2016-06-27", "Volume": "14400", "Adj_Close": "27.029069", "Symbol": "WTFCM"}, {"High": "29.198", "Open": "28.790001", "Close": "28.51", "Low": "28.50", "Date": "2016-06-24", "Volume": "25200", "Adj_Close": "27.287491", "Symbol": "WTFCM"}, {"High": "29.17", "Open": "29.17", "Close": "28.959999", "Low": "28.254999", "Date": "2016-06-23", "Volume": "19000", "Adj_Close": "27.718194", "Symbol": "WTFCM"}, {"High": "29.33", "Open": "29.18", "Close": "29.215", "Low": "29.00", "Date": "2016-06-22", "Volume": "17000", "Adj_Close": "27.962261", "Symbol": "WTFCM"}, {"High": "29.511", "Open": "29.50", "Close": "29.440001", "Low": "29.01", "Date": "2016-06-21", "Volume": "6400", "Adj_Close": "28.177613", "Symbol": "WTFCM"}, {"High": "29.59", "Open": "28.666", "Close": "29.50", "Low": "28.666", "Date": "2016-06-20", "Volume": "10200", "Adj_Close": "28.23504", "Symbol": "WTFCM"}, {"High": "29.58", "Open": "29.00", "Close": "29.50", "Low": "28.82", "Date": "2016-06-17", "Volume": "20700", "Adj_Close": "28.23504", "Symbol": "WTFCM"}, {"High": "29.049999", "Open": "28.389", "Close": "28.99", "Low": "28.25", "Date": "2016-06-16", "Volume": "21600", "Adj_Close": "27.746909", "Symbol": "WTFCM"}, {"High": "29.049999", "Open": "28.940001", "Close": "29.040001", "Low": "28.794001", "Date": "2016-06-15", "Volume": "13500", "Adj_Close": "27.794766", "Symbol": "WTFCM"}, {"High": "29.00", "Open": "28.370001", "Close": "28.950001", "Low": "28.360001", "Date": "2016-06-14", "Volume": "4600", "Adj_Close": "27.708625", "Symbol": "WTFCM"}, {"High": "28.65", "Open": "28.253", "Close": "28.60", "Low": "28.247999", "Date": "2016-06-13", "Volume": "5600", "Adj_Close": "27.373632", "Symbol": "WTFCM"}, {"High": "28.76", "Open": "28.76", "Close": "28.65", "Low": "28.08", "Date": "2016-06-10", "Volume": "35900", "Adj_Close": "27.421488", "Symbol": "WTFCM"}, {"High": "29.00", "Open": "29.00", "Close": "28.959999", "Low": "28.50", "Date": "2016-06-09", "Volume": "10600", "Adj_Close": "27.718194", "Symbol": "WTFCM"}, {"High": "29.139999", "Open": "28.700001", "Close": "29.049999", "Low": "28.700001", "Date": "2016-06-08", "Volume": "19800", "Adj_Close": "27.804335", "Symbol": "WTFCM"}, {"High": "28.745001", "Open": "28.261", "Close": "28.74", "Low": "28.261", "Date": "2016-06-07", "Volume": "16100", "Adj_Close": "27.507629", "Symbol": "WTFCM"}, {"High": "28.879999", "Open": "28.799999", "Close": "28.700001", "Low": "28.700001", "Date": "2016-06-06", "Volume": "15300", "Adj_Close": "27.469345", "Symbol": "WTFCM"}, {"High": "29.209999", "Open": "28.290001", "Close": "28.959999", "Low": "28.27", "Date": "2016-06-03", "Volume": "18100", "Adj_Close": "27.718194", "Symbol": "WTFCM"}, {"High": "28.290001", "Open": "28.117001", "Close": "28.290001", "Low": "27.879999", "Date": "2016-06-02", "Volume": "6200", "Adj_Close": "27.076926", "Symbol": "WTFCM"}, {"High": "28.299999", "Open": "28.190001", "Close": "28.030001", "Low": "27.628", "Date": "2016-06-01", "Volume": "42900", "Adj_Close": "26.828074", "Symbol": "WTFCM"}, {"High": "28.299999", "Open": "28.26", "Close": "28.299999", "Low": "27.719999", "Date": "2016-05-31", "Volume": "7700", "Adj_Close": "27.086495", "Symbol": "WTFCM"}, {"High": "28.24", "Open": "28.129999", "Close": "28.08", "Low": "28.08", "Date": "2016-05-27", "Volume": "4700", "Adj_Close": "26.87593", "Symbol": "WTFCM"}, {"High": "28.267", "Open": "28.07", "Close": "28.145", "Low": "27.969999", "Date": "2016-05-26", "Volume": "6400", "Adj_Close": "26.938143", "Symbol": "WTFCM"}, {"High": "28.50", "Open": "28.50", "Close": "28.07", "Low": "27.940001", "Date": "2016-05-25", "Volume": "21000", "Adj_Close": "26.866358", "Symbol": "WTFCM"}, {"High": "28.629999", "Open": "28.549999", "Close": "28.48", "Low": "28.16", "Date": "2016-05-24", "Volume": "14100", "Adj_Close": "27.258777", "Symbol": "WTFCM"}, {"High": "28.75", "Open": "28.34", "Close": "28.66", "Low": "28.125999", "Date": "2016-05-23", "Volume": "10600", "Adj_Close": "27.431059", "Symbol": "WTFCM"}, {"High": "28.360001", "Open": "27.73", "Close": "28.26", "Low": "27.391001", "Date": "2016-05-20", "Volume": "12700", "Adj_Close": "27.048211", "Symbol": "WTFCM"}, {"High": "27.882", "Open": "27.32", "Close": "27.66", "Low": "27.110001", "Date": "2016-05-19", "Volume": "10600", "Adj_Close": "26.473939", "Symbol": "WTFCM"}, {"High": "27.99", "Open": "27.959999", "Close": "27.290001", "Low": "27.15", "Date": "2016-05-18", "Volume": "9700", "Adj_Close": "26.119806", "Symbol": "WTFCM"}, {"High": "27.99", "Open": "27.790001", "Close": "27.959999", "Low": "27.40", "Date": "2016-05-17", "Volume": "7700", "Adj_Close": "26.761074", "Symbol": "WTFCM"}, {"High": "27.99", "Open": "27.809999", "Close": "27.746", "Low": "27.60", "Date": "2016-05-16", "Volume": "6300", "Adj_Close": "26.556252", "Symbol": "WTFCM"}, {"High": "27.85", "Open": "27.60", "Close": "27.82", "Low": "27.129999", "Date": "2016-05-13", "Volume": "14100", "Adj_Close": "26.627078", "Symbol": "WTFCM"}, {"High": "27.76", "Open": "27.398001", "Close": "27.677", "Low": "27.398001", "Date": "2016-05-12", "Volume": "6100", "Adj_Close": "26.49021", "Symbol": "WTFCM"}, {"High": "27.790001", "Open": "27.530001", "Close": "27.790001", "Low": "27.249001", "Date": "2016-05-11", "Volume": "34300", "Adj_Close": "26.598366", "Symbol": "WTFCM"}, {"High": "27.92", "Open": "27.92", "Close": "27.77", "Low": "27.17", "Date": "2016-05-10", "Volume": "29600", "Adj_Close": "26.579223", "Symbol": "WTFCM"}, {"High": "27.99", "Open": "27.370001", "Close": "27.77", "Low": "27.110001", "Date": "2016-05-09", "Volume": "5100", "Adj_Close": "26.579223", "Symbol": "WTFCM"}, {"High": "27.969999", "Open": "27.58", "Close": "27.575001", "Low": "27.575001", "Date": "2016-05-06", "Volume": "15700", "Adj_Close": "26.392585", "Symbol": "WTFCM"}, {"High": "27.85", "Open": "27.85", "Close": "27.60", "Low": "27.540001", "Date": "2016-05-05", "Volume": "5400", "Adj_Close": "26.416512", "Symbol": "WTFCM"}, {"High": "27.85", "Open": "27.719999", "Close": "27.84", "Low": "27.60", "Date": "2016-05-04", "Volume": "6400", "Adj_Close": "26.646221", "Symbol": "WTFCM"}, {"High": "27.82", "Open": "27.709999", "Close": "27.799999", "Low": "27.66", "Date": "2016-05-03", "Volume": "8100", "Adj_Close": "26.607935", "Symbol": "WTFCM"}, {"High": "27.85", "Open": "27.620001", "Close": "27.83", "Low": "27.469999", "Date": "2016-05-02", "Volume": "12900", "Adj_Close": "26.63665", "Symbol": "WTFCM"}, {"High": "27.74", "Open": "27.65", "Close": "27.40", "Low": "27.02", "Date": "2016-04-29", "Volume": "13000", "Adj_Close": "26.225088", "Symbol": "WTFCM"}, {"High": "27.68", "Open": "27.620001", "Close": "27.67", "Low": "27.26", "Date": "2016-04-28", "Volume": "22100", "Adj_Close": "26.483511", "Symbol": "WTFCM"}, {"High": "27.85", "Open": "27.450001", "Close": "27.85", "Low": "27.438999", "Date": "2016-04-27", "Volume": "13300", "Adj_Close": "26.655792", "Symbol": "WTFCM"}, {"High": "27.51", "Open": "27.51", "Close": "27.465", "Low": "27.059999", "Date": "2016-04-26", "Volume": "8400", "Adj_Close": "26.287301", "Symbol": "WTFCM"}, {"High": "27.723", "Open": "27.530001", "Close": "27.52", "Low": "27.40", "Date": "2016-04-25", "Volume": "6200", "Adj_Close": "26.339943", "Symbol": "WTFCM"}, {"High": "27.723", "Open": "27.32", "Close": "27.60", "Low": "27.32", "Date": "2016-04-22", "Volume": "8900", "Adj_Close": "26.416512", "Symbol": "WTFCM"}, {"High": "27.389999", "Open": "27.059999", "Close": "27.120001", "Low": "27.00", "Date": "2016-04-21", "Volume": "14000", "Adj_Close": "25.957095", "Symbol": "WTFCM"}, {"High": "27.496", "Open": "27.42", "Close": "27.35", "Low": "27.00", "Date": "2016-04-20", "Volume": "19900", "Adj_Close": "26.177232", "Symbol": "WTFCM"}, {"High": "27.549999", "Open": "27.43", "Close": "27.219999", "Low": "27.01", "Date": "2016-04-19", "Volume": "15000", "Adj_Close": "26.052806", "Symbol": "WTFCM"}, {"High": "27.735001", "Open": "27.57", "Close": "27.50", "Low": "27.00", "Date": "2016-04-18", "Volume": "16800", "Adj_Close": "26.3208", "Symbol": "WTFCM"}, {"High": "27.60", "Open": "27.48", "Close": "27.60", "Low": "27.094", "Date": "2016-04-15", "Volume": "9300", "Adj_Close": "26.416512", "Symbol": "WTFCM"}, {"High": "27.379999", "Open": "27.35", "Close": "27.290001", "Low": "26.90", "Date": "2016-04-14", "Volume": "9100", "Adj_Close": "26.119806", "Symbol": "WTFCM"}, {"High": "27.49", "Open": "27.49", "Close": "27.290001", "Low": "27.25", "Date": "2016-04-13", "Volume": "15900", "Adj_Close": "26.119806", "Symbol": "WTFCM"}, {"High": "27.396", "Open": "27.09", "Close": "27.360001", "Low": "27.09", "Date": "2016-04-12", "Volume": "7500", "Adj_Close": "26.186804", "Symbol": "WTFCM"}, {"High": "27.351", "Open": "26.860001", "Close": "27.07", "Low": "26.75", "Date": "2016-04-11", "Volume": "4100", "Adj_Close": "25.909238", "Symbol": "WTFCM"}, {"High": "27.282", "Open": "26.879999", "Close": "26.700001", "Low": "26.66", "Date": "2016-04-08", "Volume": "11200", "Adj_Close": "25.555105", "Symbol": "WTFCM"}, {"High": "27.289", "Open": "27.049999", "Close": "26.709999", "Low": "26.66", "Date": "2016-04-07", "Volume": "8700", "Adj_Close": "25.564674", "Symbol": "WTFCM"}, {"High": "27.299999", "Open": "27.059999", "Close": "27.09", "Low": "26.75", "Date": "2016-04-06", "Volume": "10400", "Adj_Close": "25.928381", "Symbol": "WTFCM"}, {"High": "27.108", "Open": "26.16", "Close": "27.08", "Low": "26.16", "Date": "2016-04-05", "Volume": "5700", "Adj_Close": "25.91881", "Symbol": "WTFCM"}, {"High": "27.35", "Open": "27.190001", "Close": "27.190001", "Low": "26.83", "Date": "2016-04-04", "Volume": "4800", "Adj_Close": "26.024093", "Symbol": "WTFCM"}, {"High": "27.40", "Open": "27.278999", "Close": "27.16", "Low": "26.497", "Date": "2016-04-01", "Volume": "7600", "Adj_Close": "25.995379", "Symbol": "WTFCM"}, {"High": "27.450001", "Open": "27.299999", "Close": "27.195", "Low": "26.527", "Date": "2016-03-31", "Volume": "5400", "Adj_Close": "26.028878", "Symbol": "WTFCM"}, {"High": "27.486", "Open": "27.209999", "Close": "27.299999", "Low": "26.302", "Date": "2016-03-30", "Volume": "7900", "Adj_Close": "26.129375", "Symbol": "WTFCM"}, {"High": "27.50", "Open": "27.50", "Close": "27.40", "Low": "26.723", "Date": "2016-03-29", "Volume": "15400", "Adj_Close": "25.832667", "Symbol": "WTFCM"}, {"High": "27.50", "Open": "27.496", "Close": "27.49", "Low": "26.66", "Date": "2016-03-28", "Volume": "11800", "Adj_Close": "25.917519", "Symbol": "WTFCM"}, {"High": "27.50", "Open": "27.50", "Close": "27.49", "Low": "27.094999", "Date": "2016-03-24", "Volume": "10000", "Adj_Close": "25.917519", "Symbol": "WTFCM"}, {"High": "27.622", "Open": "27.285999", "Close": "27.40", "Low": "27.219999", "Date": "2016-03-23", "Volume": "7900", "Adj_Close": "25.832667", "Symbol": "WTFCM"}, {"High": "27.83", "Open": "27.48", "Close": "27.790001", "Low": "27.25", "Date": "2016-03-22", "Volume": "8500", "Adj_Close": "26.200359", "Symbol": "WTFCM"}, {"High": "27.50", "Open": "27.50", "Close": "27.222", "Low": "27.049999", "Date": "2016-03-21", "Volume": "8000", "Adj_Close": "25.664849", "Symbol": "WTFCM"}, {"High": "27.813999", "Open": "27.23", "Close": "27.379999", "Low": "27.121", "Date": "2016-03-18", "Volume": "13800", "Adj_Close": "25.813811", "Symbol": "WTFCM"}, {"High": "27.436001", "Open": "27.200001", "Close": "27.02", "Low": "27.02", "Date": "2016-03-17", "Volume": "11900", "Adj_Close": "25.474405", "Symbol": "WTFCM"}, {"High": "27.200001", "Open": "27.08", "Close": "27.16", "Low": "26.768", "Date": "2016-03-16", "Volume": "5000", "Adj_Close": "25.606396", "Symbol": "WTFCM"}, {"High": "27.08", "Open": "26.82", "Close": "27.00", "Low": "26.799999", "Date": "2016-03-15", "Volume": "6800", "Adj_Close": "25.455548", "Symbol": "WTFCM"}, {"High": "27.120001", "Open": "27.120001", "Close": "27.00", "Low": "26.75", "Date": "2016-03-14", "Volume": "11600", "Adj_Close": "25.455548", "Symbol": "WTFCM"}, {"High": "27.200001", "Open": "27.08", "Close": "27.120001", "Low": "27.007999", "Date": "2016-03-11", "Volume": "15800", "Adj_Close": "25.568685", "Symbol": "WTFCM"}, {"High": "27.195999", "Open": "27.195999", "Close": "26.92", "Low": "26.549999", "Date": "2016-03-10", "Volume": "4300", "Adj_Close": "25.380124", "Symbol": "WTFCM"}, {"High": "26.959999", "Open": "26.620001", "Close": "26.85", "Low": "26.60", "Date": "2016-03-09", "Volume": "8200", "Adj_Close": "25.314129", "Symbol": "WTFCM"}, {"High": "26.950001", "Open": "26.91", "Close": "26.940001", "Low": "26.424999", "Date": "2016-03-08", "Volume": "6700", "Adj_Close": "25.398981", "Symbol": "WTFCM"}, {"High": "27.110001", "Open": "26.223", "Close": "26.610001", "Low": "26.110001", "Date": "2016-03-07", "Volume": "4100", "Adj_Close": "25.087857", "Symbol": "WTFCM"}, {"High": "27.195999", "Open": "26.92", "Close": "27.16", "Low": "26.85", "Date": "2016-03-04", "Volume": "4100", "Adj_Close": "25.606396", "Symbol": "WTFCM"}, {"High": "27.186001", "Open": "26.209999", "Close": "26.99", "Low": "26.209999", "Date": "2016-03-03", "Volume": "6800", "Adj_Close": "25.44612", "Symbol": "WTFCM"}, {"High": "27.00", "Open": "26.577999", "Close": "26.856001", "Low": "26.50", "Date": "2016-03-02", "Volume": "9000", "Adj_Close": "25.319786", "Symbol": "WTFCM"}, {"High": "27.49", "Open": "26.893999", "Close": "27.450001", "Low": "26.652", "Date": "2016-03-01", "Volume": "11100", "Adj_Close": "25.879808", "Symbol": "WTFCM"}, {"High": "27.10", "Open": "26.99", "Close": "26.950001", "Low": "26.50", "Date": "2016-02-29", "Volume": "20700", "Adj_Close": "25.408409", "Symbol": "WTFCM"}, {"High": "26.952999", "Open": "26.712", "Close": "26.889999", "Low": "26.054001", "Date": "2016-02-26", "Volume": "9400", "Adj_Close": "25.35184", "Symbol": "WTFCM"}, {"High": "26.969999", "Open": "26.09", "Close": "26.969999", "Low": "26.08", "Date": "2016-02-25", "Volume": "11200", "Adj_Close": "25.427264", "Symbol": "WTFCM"}, {"High": "26.65", "Open": "26.65", "Close": "26.389999", "Low": "26.075001", "Date": "2016-02-24", "Volume": "5100", "Adj_Close": "24.880441", "Symbol": "WTFCM"}, {"High": "26.639999", "Open": "26.35", "Close": "26.57", "Low": "26.35", "Date": "2016-02-23", "Volume": "7200", "Adj_Close": "25.050145", "Symbol": "WTFCM"}, {"High": "26.65", "Open": "26.086", "Close": "26.59", "Low": "26.086", "Date": "2016-02-22", "Volume": "2900", "Adj_Close": "25.069001", "Symbol": "WTFCM"}, {"High": "26.50", "Open": "25.968", "Close": "26.50", "Low": "25.874001", "Date": "2016-02-19", "Volume": "12000", "Adj_Close": "24.984149", "Symbol": "WTFCM"}, {"High": "26.65", "Open": "26.280001", "Close": "26.290001", "Low": "26.065001", "Date": "2016-02-18", "Volume": "10200", "Adj_Close": "24.786162", "Symbol": "WTFCM"}, {"High": "26.60", "Open": "26.280001", "Close": "26.59", "Low": "25.959999", "Date": "2016-02-17", "Volume": "13300", "Adj_Close": "25.069001", "Symbol": "WTFCM"}, {"High": "25.93", "Open": "25.799999", "Close": "25.73", "Low": "25.620001", "Date": "2016-02-16", "Volume": "9200", "Adj_Close": "24.258194", "Symbol": "WTFCM"}, {"High": "25.50", "Open": "25.353001", "Close": "25.492001", "Low": "25.25", "Date": "2016-02-12", "Volume": "7700", "Adj_Close": "24.033809", "Symbol": "WTFCM"}, {"High": "26.00", "Open": "25.809999", "Close": "25.09", "Low": "24.860001", "Date": "2016-02-11", "Volume": "16100", "Adj_Close": "23.654804", "Symbol": "WTFCM"}, {"High": "26.190001", "Open": "25.799999", "Close": "25.90", "Low": "25.799999", "Date": "2016-02-10", "Volume": "5700", "Adj_Close": "24.41847", "Symbol": "WTFCM"}, {"High": "25.950001", "Open": "25.549999", "Close": "25.799999", "Low": "25.459999", "Date": "2016-02-09", "Volume": "9100", "Adj_Close": "24.32419", "Symbol": "WTFCM"}, {"High": "26.469999", "Open": "26.450001", "Close": "25.98", "Low": "25.26", "Date": "2016-02-08", "Volume": "11700", "Adj_Close": "24.493894", "Symbol": "WTFCM"}, {"High": "26.898001", "Open": "26.749001", "Close": "26.450001", "Low": "26.450001", "Date": "2016-02-05", "Volume": "7100", "Adj_Close": "24.93701", "Symbol": "WTFCM"}, {"High": "26.99", "Open": "26.959999", "Close": "26.790001", "Low": "26.67", "Date": "2016-02-04", "Volume": "16000", "Adj_Close": "25.257561", "Symbol": "WTFCM"}, {"High": "26.940001", "Open": "26.60", "Close": "26.92", "Low": "26.60", "Date": "2016-02-03", "Volume": "11000", "Adj_Close": "25.380124", "Symbol": "WTFCM"}, {"High": "26.950001", "Open": "26.806", "Close": "26.90", "Low": "26.709999", "Date": "2016-02-02", "Volume": "11400", "Adj_Close": "25.361268", "Symbol": "WTFCM"}, {"High": "27.15", "Open": "26.700001", "Close": "26.879999", "Low": "26.50", "Date": "2016-02-01", "Volume": "13800", "Adj_Close": "25.342412", "Symbol": "WTFCM"}, {"High": "26.700001", "Open": "26.690001", "Close": "26.700001", "Low": "26.348", "Date": "2016-01-29", "Volume": "6700", "Adj_Close": "25.172709", "Symbol": "WTFCM"}, {"High": "26.50", "Open": "25.99", "Close": "26.50", "Low": "25.950001", "Date": "2016-01-28", "Volume": "82900", "Adj_Close": "24.984149", "Symbol": "WTFCM"}, {"High": "26.469999", "Open": "26.455", "Close": "25.870001", "Low": "25.860001", "Date": "2016-01-27", "Volume": "6800", "Adj_Close": "24.390187", "Symbol": "WTFCM"}, {"High": "26.700001", "Open": "26.700001", "Close": "26.059999", "Low": "26.00", "Date": "2016-01-26", "Volume": "22000", "Adj_Close": "24.569317", "Symbol": "WTFCM"}, {"High": "26.75", "Open": "26.469999", "Close": "26.530001", "Low": "26.02", "Date": "2016-01-25", "Volume": "7200", "Adj_Close": "25.012434", "Symbol": "WTFCM"}, {"High": "26.700001", "Open": "25.950001", "Close": "26.530001", "Low": "25.58", "Date": "2016-01-22", "Volume": "19200", "Adj_Close": "25.012434", "Symbol": "WTFCM"}, {"High": "25.85", "Open": "25.85", "Close": "25.805", "Low": "25.50", "Date": "2016-01-21", "Volume": "3300", "Adj_Close": "24.328905", "Symbol": "WTFCM"}, {"High": "25.860001", "Open": "25.860001", "Close": "25.75", "Low": "25.48", "Date": "2016-01-20", "Volume": "12400", "Adj_Close": "24.277051", "Symbol": "WTFCM"}, {"High": "25.90", "Open": "25.90", "Close": "25.90", "Low": "25.538", "Date": "2016-01-19", "Volume": "6800", "Adj_Close": "24.41847", "Symbol": "WTFCM"}, {"High": "25.90", "Open": "25.90", "Close": "25.879999", "Low": "25.559999", "Date": "2016-01-15", "Volume": "20000", "Adj_Close": "24.399613", "Symbol": "WTFCM"}, {"High": "26.246", "Open": "25.90", "Close": "25.92", "Low": "25.90", "Date": "2016-01-14", "Volume": "4800", "Adj_Close": "24.437326", "Symbol": "WTFCM"}, {"High": "26.396", "Open": "26.030001", "Close": "25.90", "Low": "25.90", "Date": "2016-01-13", "Volume": "11300", "Adj_Close": "24.41847", "Symbol": "WTFCM"}, {"High": "26.690001", "Open": "26.309999", "Close": "26.25", "Low": "26.013", "Date": "2016-01-12", "Volume": "31300", "Adj_Close": "24.74845", "Symbol": "WTFCM"}, {"High": "26.75", "Open": "26.66", "Close": "26.66", "Low": "26.59", "Date": "2016-01-11", "Volume": "4900", "Adj_Close": "25.134997", "Symbol": "WTFCM"}, {"High": "26.85", "Open": "26.549999", "Close": "26.650999", "Low": "26.549999", "Date": "2016-01-08", "Volume": "12200", "Adj_Close": "25.126511", "Symbol": "WTFCM"}, {"High": "26.90", "Open": "26.40", "Close": "26.75", "Low": "26.038", "Date": "2016-01-07", "Volume": "6600", "Adj_Close": "25.219849", "Symbol": "WTFCM"}, {"High": "26.99", "Open": "26.40", "Close": "26.799999", "Low": "26.40", "Date": "2016-01-06", "Volume": "6600", "Adj_Close": "25.266988", "Symbol": "WTFCM"}, {"High": "26.719999", "Open": "26.68", "Close": "26.718", "Low": "26.524", "Date": "2016-01-05", "Volume": "4900", "Adj_Close": "25.189679", "Symbol": "WTFCM"}, {"High": "26.66", "Open": "26.190001", "Close": "26.66", "Low": "26.190001", "Date": "2016-01-04", "Volume": "6600", "Adj_Close": "25.134997", "Symbol": "WTFCM"}, {"High": "26.719999", "Open": "26.719999", "Close": "26.59", "Low": "26.534", "Date": "2015-12-31", "Volume": "1200", "Adj_Close": "25.069001", "Symbol": "WTFCM"}, {"High": "26.690001", "Open": "26.68", "Close": "26.677", "Low": "26.610001", "Date": "2015-12-30", "Volume": "7700", "Adj_Close": "25.151024", "Symbol": "WTFCM"}, {"High": "26.700001", "Open": "26.700001", "Close": "26.676001", "Low": "26.655001", "Date": "2015-12-29", "Volume": "5200", "Adj_Close": "25.150082", "Symbol": "WTFCM"}, {"High": "26.889999", "Open": "26.809", "Close": "26.889999", "Low": "26.74", "Date": "2015-12-28", "Volume": "3200", "Adj_Close": "24.965294", "Symbol": "WTFCM"}, {"High": "26.799999", "Open": "26.490999", "Close": "26.639999", "Low": "26.490999", "Date": "2015-12-24", "Volume": "14500", "Adj_Close": "24.733188", "Symbol": "WTFCM"}, {"High": "26.599001", "Open": "26.559", "Close": "26.556", "Low": "26.469999", "Date": "2015-12-23", "Volume": "2600", "Adj_Close": "24.655201", "Symbol": "WTFCM"}, {"High": "26.596001", "Open": "26.389999", "Close": "26.58", "Low": "26.389999", "Date": "2015-12-22", "Volume": "8200", "Adj_Close": "24.677483", "Symbol": "WTFCM"}, {"High": "26.67", "Open": "26.639999", "Close": "26.51", "Low": "26.389999", "Date": "2015-12-21", "Volume": "6500", "Adj_Close": "24.612494", "Symbol": "WTFCM"}, {"High": "26.709999", "Open": "26.646999", "Close": "26.50", "Low": "26.299999", "Date": "2015-12-18", "Volume": "5100", "Adj_Close": "24.603209", "Symbol": "WTFCM"}, {"High": "26.639999", "Open": "26.40", "Close": "26.639999", "Low": "26.368", "Date": "2015-12-17", "Volume": "4400", "Adj_Close": "24.733188", "Symbol": "WTFCM"}, {"High": "26.440001", "Open": "26.190001", "Close": "26.43", "Low": "26.190001", "Date": "2015-12-16", "Volume": "4400", "Adj_Close": "24.53822", "Symbol": "WTFCM"}, {"High": "26.219999", "Open": "26.040001", "Close": "26.219999", "Low": "26.00", "Date": "2015-12-15", "Volume": "16100", "Adj_Close": "24.34325", "Symbol": "WTFCM"}, {"High": "26.568001", "Open": "26.51", "Close": "26.033001", "Low": "26.00", "Date": "2015-12-14", "Volume": "13300", "Adj_Close": "24.169637", "Symbol": "WTFCM"}, {"High": "26.636", "Open": "26.52", "Close": "26.60", "Low": "26.52", "Date": "2015-12-11", "Volume": "5300", "Adj_Close": "24.696052", "Symbol": "WTFCM"}, {"High": "26.73", "Open": "26.35", "Close": "26.709999", "Low": "26.35", "Date": "2015-12-10", "Volume": "4400", "Adj_Close": "24.798177", "Symbol": "WTFCM"}, {"High": "26.775999", "Open": "26.447001", "Close": "26.639999", "Low": "26.447001", "Date": "2015-12-09", "Volume": "5300", "Adj_Close": "24.733188", "Symbol": "WTFCM"}, {"High": "26.799999", "Open": "26.709999", "Close": "26.700001", "Low": "26.49", "Date": "2015-12-08", "Volume": "11700", "Adj_Close": "24.788894", "Symbol": "WTFCM"}, {"High": "26.690001", "Open": "26.50", "Close": "26.690001", "Low": "26.50", "Date": "2015-12-07", "Volume": "9200", "Adj_Close": "24.77961", "Symbol": "WTFCM"}, {"High": "26.700001", "Open": "26.466", "Close": "26.639999", "Low": "26.466", "Date": "2015-12-04", "Volume": "5200", "Adj_Close": "24.733188", "Symbol": "WTFCM"}, {"High": "26.697001", "Open": "26.697001", "Close": "26.610001", "Low": "26.32", "Date": "2015-12-03", "Volume": "20200", "Adj_Close": "24.705336", "Symbol": "WTFCM"}, {"High": "26.889999", "Open": "26.747", "Close": "26.690001", "Low": "26.65", "Date": "2015-12-02", "Volume": "26300", "Adj_Close": "24.77961", "Symbol": "WTFCM"}, {"High": "26.870001", "Open": "26.870001", "Close": "26.84", "Low": "26.75", "Date": "2015-12-01", "Volume": "5600", "Adj_Close": "24.918873", "Symbol": "WTFCM"}, {"High": "26.90", "Open": "26.701", "Close": "26.860001", "Low": "26.701", "Date": "2015-11-30", "Volume": "12100", "Adj_Close": "24.937442", "Symbol": "WTFCM"}, {"High": "26.93", "Open": "26.65", "Close": "26.93", "Low": "26.65", "Date": "2015-11-27", "Volume": "8400", "Adj_Close": "25.002431", "Symbol": "WTFCM"}, {"High": "26.790001", "Open": "26.75", "Close": "26.790001", "Low": "26.68", "Date": "2015-11-25", "Volume": "14000", "Adj_Close": "24.872453", "Symbol": "WTFCM"}, {"High": "26.790001", "Open": "26.589001", "Close": "26.77", "Low": "26.554001", "Date": "2015-11-24", "Volume": "25900", "Adj_Close": "24.853884", "Symbol": "WTFCM"}, {"High": "26.77", "Open": "26.77", "Close": "26.65", "Low": "26.549999", "Date": "2015-11-23", "Volume": "10200", "Adj_Close": "24.742472", "Symbol": "WTFCM"}, {"High": "26.790001", "Open": "26.625999", "Close": "26.68", "Low": "26.559999", "Date": "2015-11-20", "Volume": "10400", "Adj_Close": "24.770326", "Symbol": "WTFCM"}, {"High": "26.700001", "Open": "26.441999", "Close": "26.65", "Low": "26.441999", "Date": "2015-11-19", "Volume": "10600", "Adj_Close": "24.742472", "Symbol": "WTFCM"}, {"High": "26.65", "Open": "26.459999", "Close": "26.639999", "Low": "26.41", "Date": "2015-11-18", "Volume": "29500", "Adj_Close": "24.733188", "Symbol": "WTFCM"}, {"High": "26.73", "Open": "26.40", "Close": "26.58", "Low": "26.40", "Date": "2015-11-17", "Volume": "33700", "Adj_Close": "24.677483", "Symbol": "WTFCM"}, {"High": "26.700001", "Open": "26.620001", "Close": "26.49", "Low": "26.389999", "Date": "2015-11-16", "Volume": "54900", "Adj_Close": "24.593925", "Symbol": "WTFCM"}, {"High": "26.66", "Open": "26.559999", "Close": "26.59", "Low": "26.51", "Date": "2015-11-13", "Volume": "41900", "Adj_Close": "24.686767", "Symbol": "WTFCM"}, {"High": "26.549999", "Open": "26.450001", "Close": "26.540001", "Low": "26.40", "Date": "2015-11-12", "Volume": "19100", "Adj_Close": "24.640347", "Symbol": "WTFCM"}, {"High": "26.58", "Open": "26.48", "Close": "26.49", "Low": "26.450001", "Date": "2015-11-11", "Volume": "30900", "Adj_Close": "24.593925", "Symbol": "WTFCM"}, {"High": "26.469999", "Open": "26.344", "Close": "26.469999", "Low": "26.26", "Date": "2015-11-10", "Volume": "28800", "Adj_Close": "24.575356", "Symbol": "WTFCM"}, {"High": "26.365", "Open": "26.10", "Close": "26.34", "Low": "26.030001", "Date": "2015-11-09", "Volume": "32400", "Adj_Close": "24.454662", "Symbol": "WTFCM"}, {"High": "26.27", "Open": "26.195999", "Close": "26.237", "Low": "26.059999", "Date": "2015-11-06", "Volume": "63100", "Adj_Close": "24.359033", "Symbol": "WTFCM"}, {"High": "26.26", "Open": "26.24", "Close": "26.23", "Low": "26.00", "Date": "2015-11-05", "Volume": "54700", "Adj_Close": "24.352535", "Symbol": "WTFCM"}, {"High": "26.27", "Open": "26.15", "Close": "26.24", "Low": "26.02", "Date": "2015-11-04", "Volume": "23600", "Adj_Close": "24.361819", "Symbol": "WTFCM"}, {"High": "26.16", "Open": "26.030001", "Close": "26.08", "Low": "25.969999", "Date": "2015-11-03", "Volume": "86500", "Adj_Close": "24.213271", "Symbol": "WTFCM"}, {"High": "26.08", "Open": "25.85", "Close": "25.93", "Low": "25.826", "Date": "2015-11-02", "Volume": "36700", "Adj_Close": "24.074008", "Symbol": "WTFCM"}, {"High": "25.879999", "Open": "25.799999", "Close": "25.809999", "Low": "25.75", "Date": "2015-10-30", "Volume": "14500", "Adj_Close": "23.962597", "Symbol": "WTFCM"}, {"High": "25.83", "Open": "25.780001", "Close": "25.83", "Low": "25.700001", "Date": "2015-10-29", "Volume": "376900", "Adj_Close": "23.981166", "Symbol": "WTFCM"}, {"High": "25.809999", "Open": "25.719999", "Close": "25.809999", "Low": "25.68", "Date": "2015-10-28", "Volume": "32100", "Adj_Close": "23.962597", "Symbol": "WTFCM"}, {"High": "25.73", "Open": "25.60", "Close": "25.629999", "Low": "25.60", "Date": "2015-10-27", "Volume": "29700", "Adj_Close": "23.79548", "Symbol": "WTFCM"}, {"High": "25.65", "Open": "25.58", "Close": "25.59", "Low": "25.561001", "Date": "2015-10-26", "Volume": "15500", "Adj_Close": "23.758344", "Symbol": "WTFCM"}, {"High": "25.719999", "Open": "25.540001", "Close": "25.629999", "Low": "25.540001", "Date": "2015-10-23", "Volume": "22200", "Adj_Close": "23.79548", "Symbol": "WTFCM"}, {"High": "25.66", "Open": "25.60", "Close": "25.559999", "Low": "25.52", "Date": "2015-10-22", "Volume": "54300", "Adj_Close": "23.730491", "Symbol": "WTFCM"}, {"High": "25.620001", "Open": "25.58", "Close": "25.51", "Low": "25.469999", "Date": "2015-10-21", "Volume": "36500", "Adj_Close": "23.684071", "Symbol": "WTFCM"}, {"High": "25.65", "Open": "25.559999", "Close": "25.59", "Low": "25.50", "Date": "2015-10-20", "Volume": "48800", "Adj_Close": "23.758344", "Symbol": "WTFCM"}, {"High": "25.74", "Open": "25.65", "Close": "25.52", "Low": "25.459999", "Date": "2015-10-19", "Volume": "44200", "Adj_Close": "23.693355", "Symbol": "WTFCM"}, {"High": "26.26", "Open": "25.969999", "Close": "25.559999", "Low": "25.50", "Date": "2015-10-16", "Volume": "1246000", "Adj_Close": "23.730491", "Symbol": "WTFCM"}, {"High": "26.35", "Open": "26.139999", "Close": "26.049999", "Low": "25.98", "Date": "2015-10-15", "Volume": "32900", "Adj_Close": "24.185418", "Symbol": "WTFCM"}, {"High": "26.17", "Open": "26.139999", "Close": "26.059999", "Low": "25.974001", "Date": "2015-10-14", "Volume": "18400", "Adj_Close": "24.194703", "Symbol": "WTFCM"}, {"High": "26.16", "Open": "26.059999", "Close": "26.15", "Low": "25.950001", "Date": "2015-10-13", "Volume": "29700", "Adj_Close": "24.278261", "Symbol": "WTFCM"}, {"High": "25.99", "Open": "25.92", "Close": "25.959999", "Low": "25.879999", "Date": "2015-10-12", "Volume": "21600", "Adj_Close": "24.10186", "Symbol": "WTFCM"}, {"High": "25.940001", "Open": "25.91", "Close": "25.91", "Low": "25.790001", "Date": "2015-10-09", "Volume": "50600", "Adj_Close": "24.055439", "Symbol": "WTFCM"}, {"High": "25.940001", "Open": "25.837999", "Close": "25.889999", "Low": "25.781", "Date": "2015-10-08", "Volume": "20200", "Adj_Close": "24.036871", "Symbol": "WTFCM"}, {"High": "25.940001", "Open": "25.91", "Close": "25.90", "Low": "25.799999", "Date": "2015-10-07", "Volume": "62100", "Adj_Close": "24.046155", "Symbol": "WTFCM"}, {"High": "25.940001", "Open": "25.90", "Close": "25.90", "Low": "25.780001", "Date": "2015-10-06", "Volume": "39300", "Adj_Close": "24.046155", "Symbol": "WTFCM"}, {"High": "25.90", "Open": "25.559999", "Close": "25.860001", "Low": "25.549999", "Date": "2015-10-05", "Volume": "108400", "Adj_Close": "24.009019", "Symbol": "WTFCM"}, {"High": "25.620001", "Open": "25.389999", "Close": "25.51", "Low": "25.360001", "Date": "2015-10-02", "Volume": "84100", "Adj_Close": "23.684071", "Symbol": "WTFCM"}, {"High": "25.60", "Open": "25.40", "Close": "25.584999", "Low": "25.33", "Date": "2015-10-01", "Volume": "32600", "Adj_Close": "23.753701", "Symbol": "WTFCM"}, {"High": "25.74", "Open": "25.202999", "Close": "25.50", "Low": "25.201", "Date": "2015-09-30", "Volume": "54100", "Adj_Close": "23.674786", "Symbol": "WTFCM"}, {"High": "25.309999", "Open": "25.309999", "Close": "25.27", "Low": "25.209999", "Date": "2015-09-29", "Volume": "27300", "Adj_Close": "23.461249", "Symbol": "WTFCM"}, {"High": "25.690001", "Open": "25.629999", "Close": "25.690001", "Low": "25.60", "Date": "2015-09-28", "Volume": "2400", "Adj_Close": "23.386975", "Symbol": "WTFCM"}, {"High": "25.719999", "Open": "25.549999", "Close": "25.709999", "Low": "25.549999", "Date": "2015-09-25", "Volume": "19700", "Adj_Close": "23.405181", "Symbol": "WTFCM"}, {"High": "25.67", "Open": "25.610001", "Close": "25.67", "Low": "25.59", "Date": "2015-09-24", "Volume": "12400", "Adj_Close": "23.368768", "Symbol": "WTFCM"}, {"High": "25.629999", "Open": "25.52", "Close": "25.620001", "Low": "25.52", "Date": "2015-09-23", "Volume": "12800", "Adj_Close": "23.323251", "Symbol": "WTFCM"}, {"High": "25.57", "Open": "25.530001", "Close": "25.559999", "Low": "25.530001", "Date": "2015-09-22", "Volume": "15100", "Adj_Close": "23.268628", "Symbol": "WTFCM"}, {"High": "25.57", "Open": "25.540001", "Close": "25.549999", "Low": "25.459999", "Date": "2015-09-21", "Volume": "11200", "Adj_Close": "23.259525", "Symbol": "WTFCM"}, {"High": "25.59", "Open": "25.379999", "Close": "25.540001", "Low": "25.35", "Date": "2015-09-18", "Volume": "26500", "Adj_Close": "23.250423", "Symbol": "WTFCM"}, {"High": "25.389999", "Open": "25.280001", "Close": "25.379999", "Low": "25.280001", "Date": "2015-09-17", "Volume": "14300", "Adj_Close": "23.104765", "Symbol": "WTFCM"}, {"High": "25.450001", "Open": "25.434", "Close": "25.280001", "Low": "25.268", "Date": "2015-09-16", "Volume": "17100", "Adj_Close": "23.013731", "Symbol": "WTFCM"}, {"High": "25.40", "Open": "25.280001", "Close": "25.35", "Low": "25.280001", "Date": "2015-09-15", "Volume": "3800", "Adj_Close": "23.077455", "Symbol": "WTFCM"}, {"High": "25.360001", "Open": "25.26", "Close": "25.290001", "Low": "25.26", "Date": "2015-09-14", "Volume": "9800", "Adj_Close": "23.022834", "Symbol": "WTFCM"}, {"High": "25.389999", "Open": "25.26", "Close": "25.26", "Low": "25.26", "Date": "2015-09-11", "Volume": "7200", "Adj_Close": "22.995523", "Symbol": "WTFCM"}, {"High": "25.402", "Open": "25.389999", "Close": "25.35", "Low": "25.25", "Date": "2015-09-10", "Volume": "13600", "Adj_Close": "23.077455", "Symbol": "WTFCM"}, {"High": "25.42", "Open": "25.18", "Close": "25.41", "Low": "25.18", "Date": "2015-09-09", "Volume": "139100", "Adj_Close": "23.132076", "Symbol": "WTFCM"}, {"High": "25.42", "Open": "25.26", "Close": "25.42", "Low": "25.26", "Date": "2015-09-08", "Volume": "4500", "Adj_Close": "23.14118", "Symbol": "WTFCM"}, {"High": "25.440001", "Open": "25.40", "Close": "25.440001", "Low": "25.32", "Date": "2015-09-04", "Volume": "5900", "Adj_Close": "23.159387", "Symbol": "WTFCM"}, {"High": "25.43", "Open": "25.35", "Close": "25.40", "Low": "25.25", "Date": "2015-09-03", "Volume": "48000", "Adj_Close": "23.122972", "Symbol": "WTFCM"}, {"High": "25.34", "Open": "25.339001", "Close": "25.290001", "Low": "25.23", "Date": "2015-09-02", "Volume": "20400", "Adj_Close": "23.022834", "Symbol": "WTFCM"}, {"High": "25.389999", "Open": "25.389999", "Close": "25.285999", "Low": "25.236", "Date": "2015-09-01", "Volume": "86300", "Adj_Close": "23.019191", "Symbol": "WTFCM"}, {"High": "25.49", "Open": "25.49", "Close": "25.389999", "Low": "25.209999", "Date": "2015-08-31", "Volume": "44700", "Adj_Close": "23.113868", "Symbol": "WTFCM"}, {"High": "25.459999", "Open": "25.209999", "Close": "25.43", "Low": "25.209999", "Date": "2015-08-28", "Volume": "20000", "Adj_Close": "23.150283", "Symbol": "WTFCM"}, {"High": "25.34", "Open": "25.200001", "Close": "25.290001", "Low": "25.15", "Date": "2015-08-27", "Volume": "14200", "Adj_Close": "23.022834", "Symbol": "WTFCM"}, {"High": "25.23", "Open": "25.219999", "Close": "25.18", "Low": "25.030001", "Date": "2015-08-26", "Volume": "9800", "Adj_Close": "22.922695", "Symbol": "WTFCM"}, {"High": "25.200001", "Open": "24.950001", "Close": "25.129999", "Low": "24.950001", "Date": "2015-08-25", "Volume": "3900", "Adj_Close": "22.877176", "Symbol": "WTFCM"}, {"High": "25.32", "Open": "25.299999", "Close": "24.889999", "Low": "24.889999", "Date": "2015-08-24", "Volume": "29400", "Adj_Close": "22.658692", "Symbol": "WTFCM"}, {"High": "25.554001", "Open": "25.530001", "Close": "25.50", "Low": "25.42", "Date": "2015-08-21", "Volume": "3500", "Adj_Close": "23.214008", "Symbol": "WTFCM"}, {"High": "25.638", "Open": "25.521", "Close": "25.58", "Low": "25.41", "Date": "2015-08-20", "Volume": "18300", "Adj_Close": "23.286836", "Symbol": "WTFCM"}, {"High": "25.639999", "Open": "25.450001", "Close": "25.639999", "Low": "25.450001", "Date": "2015-08-19", "Volume": "21900", "Adj_Close": "23.341457", "Symbol": "WTFCM"}, {"High": "25.67", "Open": "25.601", "Close": "25.65", "Low": "25.60", "Date": "2015-08-18", "Volume": "7400", "Adj_Close": "23.35056", "Symbol": "WTFCM"}, {"High": "25.639999", "Open": "25.610001", "Close": "25.639999", "Low": "25.50", "Date": "2015-08-17", "Volume": "30600", "Adj_Close": "23.341457", "Symbol": "WTFCM"}, {"High": "25.75", "Open": "25.50", "Close": "25.75", "Low": "25.49", "Date": "2015-08-14", "Volume": "12700", "Adj_Close": "23.441596", "Symbol": "WTFCM"}, {"High": "25.58", "Open": "25.50", "Close": "25.549999", "Low": "25.459999", "Date": "2015-08-13", "Volume": "16200", "Adj_Close": "23.259525", "Symbol": "WTFCM"}, {"High": "25.50", "Open": "25.50", "Close": "25.49", "Low": "25.40", "Date": "2015-08-12", "Volume": "8300", "Adj_Close": "23.204904", "Symbol": "WTFCM"}, {"High": "25.58", "Open": "25.459999", "Close": "25.52", "Low": "25.309999", "Date": "2015-08-11", "Volume": "17300", "Adj_Close": "23.232215", "Symbol": "WTFCM"}, {"High": "25.690001", "Open": "25.690001", "Close": "25.59", "Low": "25.450001", "Date": "2015-08-10", "Volume": "24400", "Adj_Close": "23.29594", "Symbol": "WTFCM"}, {"High": "25.65", "Open": "25.450001", "Close": "25.58", "Low": "25.450001", "Date": "2015-08-07", "Volume": "17100", "Adj_Close": "23.286836", "Symbol": "WTFCM"}, {"High": "25.50", "Open": "25.42", "Close": "25.50", "Low": "25.370001", "Date": "2015-08-06", "Volume": "39300", "Adj_Close": "23.214008", "Symbol": "WTFCM"}, {"High": "25.40", "Open": "25.34", "Close": "25.40", "Low": "25.209999", "Date": "2015-08-05", "Volume": "73300", "Adj_Close": "23.122972", "Symbol": "WTFCM"}, {"High": "25.287001", "Open": "25.200001", "Close": "25.280001", "Low": "25.01", "Date": "2015-08-04", "Volume": "220900", "Adj_Close": "23.013731", "Symbol": "WTFCM"}, {"High": "25.24", "Open": "25.10", "Close": "25.209999", "Low": "25.077999", "Date": "2015-08-03", "Volume": "35100", "Adj_Close": "22.950004", "Symbol": "WTFCM"}, {"High": "25.18", "Open": "25.00", "Close": "25.10", "Low": "24.950001", "Date": "2015-07-31", "Volume": "43100", "Adj_Close": "22.849867", "Symbol": "WTFCM"}, {"High": "25.07", "Open": "25.00", "Close": "25.00", "Low": "24.950001", "Date": "2015-07-30", "Volume": "287500", "Adj_Close": "22.758831", "Symbol": "WTFCM"}, {"High": "25.00", "Open": "25.00", "Close": "24.90", "Low": "24.90", "Date": "2015-07-29", "Volume": "23800", "Adj_Close": "22.667795", "Symbol": "WTFCM"}, {"High": "25.030001", "Open": "25.00", "Close": "24.91", "Low": "24.90", "Date": "2015-07-28", "Volume": "48600", "Adj_Close": "22.676899", "Symbol": "WTFCM"}, {"High": "25.030001", "Open": "25.030001", "Close": "24.950001", "Low": "24.90", "Date": "2015-07-27", "Volume": "24500", "Adj_Close": "22.713314", "Symbol": "WTFCM"}, {"High": "25.10", "Open": "25.10", "Close": "24.90", "Low": "24.90", "Date": "2015-07-24", "Volume": "23900", "Adj_Close": "22.667795", "Symbol": "WTFCM"}, {"High": "25.10", "Open": "25.10", "Close": "25.049999", "Low": "24.879999", "Date": "2015-07-23", "Volume": "44100", "Adj_Close": "22.804348", "Symbol": "WTFCM"}, {"High": "25.049999", "Open": "25.049999", "Close": "24.98", "Low": "24.98", "Date": "2015-07-22", "Volume": "29500", "Adj_Close": "22.740624", "Symbol": "WTFCM"}, {"High": "25.10", "Open": "25.049999", "Close": "25.049999", "Low": "25.02", "Date": "2015-07-21", "Volume": "117100", "Adj_Close": "22.804348", "Symbol": "WTFCM"}, {"High": "25.049999", "Open": "24.90", "Close": "25.00", "Low": "24.84", "Date": "2015-07-20", "Volume": "424600", "Adj_Close": "22.758831", "Symbol": "WTFCM"}, {"High": "25.049999", "Open": "25.02", "Close": "25.030001", "Low": "24.879999", "Date": "2015-07-17", "Volume": "128900", "Adj_Close": "22.786142", "Symbol": "WTFCM"}, {"High": "25.07", "Open": "24.860001", "Close": "24.98", "Low": "24.719999", "Date": "2015-07-16", "Volume": "134500", "Adj_Close": "22.740624", "Symbol": "WTFCM"}, {"High": "24.870001", "Open": "24.639999", "Close": "24.84", "Low": "24.629999", "Date": "2015-07-15", "Volume": "138200", "Adj_Close": "22.613175", "Symbol": "WTFCM"}, {"High": "24.700001", "Open": "24.700001", "Close": "24.610001", "Low": "24.48", "Date": "2015-07-14", "Volume": "52000", "Adj_Close": "22.403794", "Symbol": "WTFCM"}, {"High": "24.719999", "Open": "24.690001", "Close": "24.60", "Low": "24.58", "Date": "2015-07-13", "Volume": "73300", "Adj_Close": "22.39469", "Symbol": "WTFCM"}, {"High": "24.700001", "Open": "24.700001", "Close": "24.690001", "Low": "24.629999", "Date": "2015-07-10", "Volume": "35000", "Adj_Close": "22.476622", "Symbol": "WTFCM"}, {"High": "24.90", "Open": "24.90", "Close": "24.68", "Low": "24.620001", "Date": "2015-07-09", "Volume": "42200", "Adj_Close": "22.467518", "Symbol": "WTFCM"}, {"High": "24.75", "Open": "24.690001", "Close": "24.68", "Low": "24.629999", "Date": "2015-07-08", "Volume": "172200", "Adj_Close": "22.467518", "Symbol": "WTFCM"}, {"High": "25.00", "Open": "24.75", "Close": "24.690001", "Low": "24.65", "Date": "2015-07-07", "Volume": "47300", "Adj_Close": "22.476622", "Symbol": "WTFCM"}, {"High": "24.799999", "Open": "24.709999", "Close": "24.67", "Low": "24.610001", "Date": "2015-07-06", "Volume": "236300", "Adj_Close": "22.458415", "Symbol": "WTFCM"}, {"High": "24.75", "Open": "24.700001", "Close": "24.700001", "Low": "24.639999", "Date": "2015-07-02", "Volume": "19900", "Adj_Close": "22.485726", "Symbol": "WTFCM"}, {"High": "24.75", "Open": "24.700001", "Close": "24.700001", "Low": "24.60", "Date": "2015-07-01", "Volume": "31400", "Adj_Close": "22.485726", "Symbol": "WTFCM"}, {"High": "24.700001", "Open": "24.700001", "Close": "24.65", "Low": "24.530001", "Date": "2015-06-30", "Volume": "123500", "Adj_Close": "22.440207", "Symbol": "WTFCM"}, {"High": "24.719999", "Open": "24.700001", "Close": "24.530001", "Low": "24.530001", "Date": "2015-06-29", "Volume": "113000", "Adj_Close": "22.330966", "Symbol": "WTFCM"}, {"High": "24.74", "Open": "24.719999", "Close": "24.690001", "Low": "24.629999", "Date": "2015-06-26", "Volume": "117500", "Adj_Close": "22.476622", "Symbol": "WTFCM"}, {"High": "24.75", "Open": "24.75", "Close": "24.690001", "Low": "24.629999", "Date": "2015-06-25", "Volume": "338700", "Adj_Close": "22.476622", "Symbol": "WTFCM"}, {"High": "24.85", "Open": "24.85", "Close": "24.68", "Low": "24.65", "Date": "2015-06-24", "Volume": "470500", "Adj_Close": "22.467518", "Symbol": "WTFCM"}]